nivel2_timer/nivel3_timer/contador_mod10.v
`timescale 1ns/1ps

module contador_mod10 (
    input wire clk,          // sinal de clock
    input wire loadn,        
  	input wire [3:0] data,   // valor inicial do contador
    input wire clearn,       // sinal de reset em nível baixo
    input wire en,           // sinal de habilitação em nível alto
    output wire tc,
    output wire zero,
  	output reg [3:0] ones // saída do contador
);

  assign zero = (ones == 4'b0000) ? 1'b1 : 1'b0;
  assign tc = en & zero;

  always @(posedge clk) begin
    if (~loadn) begin
        ones <= data; // reinicia o contador com o valor de 'data'
    end else if (~clearn) begin
        ones <= 3'b000; // zera o contador quando 'clearn' está em nível baixo
    end else if (en) begin
        if (ones == 4'b0000) begin
            ones <= 4'b1001; // volta a contar a partir de 9 quando atinge 0
        end else begin
            ones <= ones - 1; // subtrai 1 do contador
        end
    end
  end

endmodule

nivel2_timer/nivel3_timer/contador_mod6.v

module contador_mod6 (
    input wire clk,          // sinal de clock
    input wire loadn,        
  	input wire [3:0] data,   // valor inicial do contador
    input wire clearn,       // sinal de reset em nível baixo
    input wire en,           // sinal de habilitação em nível alto
    output wire tc,
    output wire zero,
  	output reg [3:0] tens // saída do contador
);

  assign zero = (tens == 4'b0000) ? 1'b1 : 1'b0;
  assign tc = en & zero;

  always @(posedge clk) begin
    if (~loadn) begin
        tens <= data; // reinicia o contador com o valor de 'data'
    end else if (~clearn) begin
        tens <= 4'b0000; // zera o contador quando 'clearn' está em nível baixo
    end else if (en) begin
        if (tens == 4'b0000) begin
            tens <= 4'b0101; // volta a contar a partir de 5 quando atinge 0
        end else begin
            tens <= tens - 1; // subtrai 1 do contador
        end
    end
  end

endmodule

nivel2_timer/timer_nivel2.v
// Importando os módulos dos contadores
`include "nivel3_timer/contador_mod10.v"
`include "nivel3_timer/contador_mod6.v"

// Definindo a escala de tempo do módulo
`timescale 1ns/1ps

// Definindo o módulo timer_nivel2
module timer_nivel2(data, clk, enable, load, clear, unidades, dezenas, minutos, zero);

  // Definindo as entradas do módulo
  input [3:0] data;
  input wire clk, enable, load, clear; // Lembrar que aqui tudo menos o clk está invertido (load equivale a loadn...)
  
  // Definindo as saídas do módulo
  output wire [3:0] unidades, dezenas, minutos;
  output wire zero;
  
  // Definindo os sinais de controle dos contadores
  wire tc1;
  wire tc2;
  wire tc3;
  
  // Definindo os sinais de saída de zero dos contadores
  wire zero1;
  wire zero2;
  wire zero3;

  // Instanciando o contador_mod10 para as unidades
  contador_mod10 unidade(clk, load, data, clear, enable, tc1, zero1, unidades);
  
  // Instanciando o contador_mod6 para as dezenas
  contador_mod6 dezena(clk, load, unidades, clear, tc1, tc2, zero2, dezenas);
  
  // Instanciando o contador_mod10 para os minutos
  contador_mod10 minuto(clk, load, dezenas, clear, tc2, tc3, zero3, minutos);

  // Definindo o sinal zero como o AND das saídas zero dos contadores
  assign zero = zero1 & zero2 & zero3;
endmodule

nivel2_timer/timer_nivel2_tb.v
`timescale 1ns/1ps
`include "timer_nivel2.v"

module timer_nivel2_tb();
  // Declaração de entradas e saídas do testbench
    wire[3:0] minutos_tb, dezenas, unidades_tb;
    wire timer_done_tb;
    reg [3:0]  data_tb;
    reg clearn_tb, enable_tb, loadn_tb, clk_tb;

    // Instanciando o DUT (Device Under Test) e suas conexões
    timer_nivel2 DUT(data_tb, clk_tb, enable_tb, loadn_tb, clearn_tb,
                  unidades_tb, dezenas, minutos_tb, timer_done_tb);

    initial begin
        $dumpfile("timer_nivel2_tb.vcd"); // Define o nome do arquivo de simulação
        $dumpvars(0,timer_nivel2_tb); // Define quais variáveis serão salvas no arquivo de simulação
        clk_tb  = 1'b0; // Inicializa o clock
        enable_tb = 1'b0; // Desabilita o timer
        loadn_tb  = 1'b0; // Desativa o sinal de carregamento
    end

    always begin
        #1 clk_tb = loadn_tb? ~clk_tb : clk_tb; // Gera o sinal de clock
    end

    initial begin    
        clearn_tb = 1'b1; #0.5 // Ativa o sinal de limpeza por 0.5ns
        clearn_tb = 1'b0; #0.5 // Desativa o sinal de limpeza por 0.5ns
        clearn_tb = 1'b1; #0.5 // Ativa novamente o sinal de limpeza por 0.5ns

        data_tb =  2;   #0.04; // Define o valor de entrada para 2 e espera 0.04ns
        clk_tb = 1'b1;   #0.01; // Gera uma borda de subida no clock por 0.01ns
        clk_tb = 1'b0;   #0.95; // Gera uma borda de descida no clock por 0.95ns

        data_tb =  0;   #0.04; // Define o valor de entrada para 0 e espera 0.04ns
        clk_tb = 1'b1;   #0.01; // Gera uma borda de subida no clock por 0.01ns
        clk_tb = 1'b0;   #0.95; // Gera uma borda de descida no clock por 0.95ns

        data_tb =  0;   #0.04; // Define o valor de entrada para 0 e espera 0.04ns
        clk_tb = 1'b1;   #0.01; // Gera uma borda de subida no clock por 0.01ns
        clk_tb = 1'b0;   #0.95; // Gera uma borda de descida no clock por 0.95ns
        enable_tb = 1; loadn_tb = 1; #1000; // Habilita o timer e ativa o sinal de carregamento por 1000ns

        $finish(); // Finaliza a simulação
    end
endmodule

nivel2_timer/timer_nivel2_tb.vcd
$date
	Sat Apr 22 20:22:16 2023
$end
$version
	Icarus Verilog
$end
$timescale
	1ps
$end
$scope module timer_nivel2_tb $end
$var wire 4 ! unidades_tb [3:0] $end
$var wire 1 " timer_done_tb $end
$var wire 4 # minutos_tb [3:0] $end
$var wire 4 $ dezenas [3:0] $end
$var reg 1 % clearn_tb $end
$var reg 1 & clk_tb $end
$var reg 4 ' data_tb [3:0] $end
$var reg 1 ( enable_tb $end
$var reg 1 ) loadn_tb $end
$scope module DUT $end
$var wire 1 % clear $end
$var wire 1 & clk $end
$var wire 4 * data [3:0] $end
$var wire 1 ( enable $end
$var wire 1 ) load $end
$var wire 1 " zero $end
$var wire 1 + zero3 $end
$var wire 1 , zero2 $end
$var wire 1 - zero1 $end
$var wire 4 . unidades [3:0] $end
$var wire 1 / tc3 $end
$var wire 1 0 tc2 $end
$var wire 1 1 tc1 $end
$var wire 4 2 minutos [3:0] $end
$var wire 4 3 dezenas [3:0] $end
$scope module dezena $end
$var wire 1 % clearn $end
$var wire 1 & clk $end
$var wire 1 ) loadn $end
$var wire 1 0 tc $end
$var wire 1 , zero $end
$var wire 1 1 en $end
$var wire 4 4 data [3:0] $end
$var reg 4 5 tens [3:0] $end
$upscope $end
$scope module minuto $end
$var wire 1 % clearn $end
$var wire 1 & clk $end
$var wire 4 6 data [3:0] $end
$var wire 1 0 en $end
$var wire 1 ) loadn $end
$var wire 1 / tc $end
$var wire 1 + zero $end
$var reg 4 7 ones [3:0] $end
$upscope $end
$scope module unidade $end
$var wire 1 % clearn $end
$var wire 1 & clk $end
$var wire 4 8 data [3:0] $end
$var wire 1 ( en $end
$var wire 1 ) loadn $end
$var wire 1 1 tc $end
$var wire 1 - zero $end
$var reg 4 9 ones [3:0] $end
$upscope $end
$upscope $end
$upscope $end
$enddefinitions $end
$comment Show the parameter values. $end
$dumpall
$end
#0
$dumpvars
bx 9
bx 8
bx 7
bx 6
bx 5
bx 4
bx 3
bx 2
01
00
0/
bx .
x-
x,
x+
bx *
0)
0(
bx '
0&
1%
bx $
bx #
x"
bx !
$end
#500
0%
#1000
1%
#1500
b10 '
b10 *
b10 8
#1540
0"
0-
b10 !
b10 .
b10 4
b10 9
1&
#1550
0&
#2500
b0 '
b0 *
b0 8
#2540
0,
1-
b10 $
b10 3
b10 5
b10 6
b0 !
b0 .
b0 4
b0 9
1&
#2550
0&
#3540
1,
0+
b0 $
b0 3
b0 5
b0 6
b10 #
b10 2
b10 7
1&
#3550
0&
#4500
10
11
1)
1(
#5000
00
01
0,
0-
b1 #
b1 2
b1 7
b101 $
b101 3
b101 5
b101 6
b1001 !
b1001 .
b1001 4
b1001 9
1&
#6000
0&
#7000
b1000 !
b1000 .
b1000 4
b1000 9
1&
#8000
0&
#9000
b111 !
b111 .
b111 4
b111 9
1&
#10000
0&
#11000
b110 !
b110 .
b110 4
b110 9
1&
#12000
0&
#13000
b101 !
b101 .
b101 4
b101 9
1&
#14000
0&
#15000
b100 !
b100 .
b100 4
b100 9
1&
#16000
0&
#17000
b11 !
b11 .
b11 4
b11 9
1&
#18000
0&
#19000
b10 !
b10 .
b10 4
b10 9
1&
#20000
0&
#21000
b1 !
b1 .
b1 4
b1 9
1&
#22000
0&
#23000
11
1-
b0 !
b0 .
b0 4
b0 9
1&
#24000
0&
#25000
01
0-
b100 $
b100 3
b100 5
b100 6
b1001 !
b1001 .
b1001 4
b1001 9
1&
#26000
0&
#27000
b1000 !
b1000 .
b1000 4
b1000 9
1&
#28000
0&
#29000
b111 !
b111 .
b111 4
b111 9
1&
#30000
0&
#31000
b110 !
b110 .
b110 4
b110 9
1&
#32000
0&
#33000
b101 !
b101 .
b101 4
b101 9
1&
#34000
0&
#35000
b100 !
b100 .
b100 4
b100 9
1&
#36000
0&
#37000
b11 !
b11 .
b11 4
b11 9
1&
#38000
0&
#39000
b10 !
b10 .
b10 4
b10 9
1&
#40000
0&
#41000
b1 !
b1 .
b1 4
b1 9
1&
#42000
0&
#43000
11
1-
b0 !
b0 .
b0 4
b0 9
1&
#44000
0&
#45000
01
0-
b11 $
b11 3
b11 5
b11 6
b1001 !
b1001 .
b1001 4
b1001 9
1&
#46000
0&
#47000
b1000 !
b1000 .
b1000 4
b1000 9
1&
#48000
0&
#49000
b111 !
b111 .
b111 4
b111 9
1&
#50000
0&
#51000
b110 !
b110 .
b110 4
b110 9
1&
#52000
0&
#53000
b101 !
b101 .
b101 4
b101 9
1&
#54000
0&
#55000
b100 !
b100 .
b100 4
b100 9
1&
#56000
0&
#57000
b11 !
b11 .
b11 4
b11 9
1&
#58000
0&
#59000
b10 !
b10 .
b10 4
b10 9
1&
#60000
0&
#61000
b1 !
b1 .
b1 4
b1 9
1&
#62000
0&
#63000
11
1-
b0 !
b0 .
b0 4
b0 9
1&
#64000
0&
#65000
01
0-
b10 $
b10 3
b10 5
b10 6
b1001 !
b1001 .
b1001 4
b1001 9
1&
#66000
0&
#67000
b1000 !
b1000 .
b1000 4
b1000 9
1&
#68000
0&
#69000
b111 !
b111 .
b111 4
b111 9
1&
#70000
0&
#71000
b110 !
b110 .
b110 4
b110 9
1&
#72000
0&
#73000
b101 !
b101 .
b101 4
b101 9
1&
#74000
0&
#75000
b100 !
b100 .
b100 4
b100 9
1&
#76000
0&
#77000
b11 !
b11 .
b11 4
b11 9
1&
#78000
0&
#79000
b10 !
b10 .
b10 4
b10 9
1&
#80000
0&
#81000
b1 !
b1 .
b1 4
b1 9
1&
#82000
0&
#83000
11
1-
b0 !
b0 .
b0 4
b0 9
1&
#84000
0&
#85000
01
0-
b1 $
b1 3
b1 5
b1 6
b1001 !
b1001 .
b1001 4
b1001 9
1&
#86000
0&
#87000
b1000 !
b1000 .
b1000 4
b1000 9
1&
#88000
0&
#89000
b111 !
b111 .
b111 4
b111 9
1&
#90000
0&
#91000
b110 !
b110 .
b110 4
b110 9
1&
#92000
0&
#93000
b101 !
b101 .
b101 4
b101 9
1&
#94000
0&
#95000
b100 !
b100 .
b100 4
b100 9
1&
#96000
0&
#97000
b11 !
b11 .
b11 4
b11 9
1&
#98000
0&
#99000
b10 !
b10 .
b10 4
b10 9
1&
#100000
0&
#101000
b1 !
b1 .
b1 4
b1 9
1&
#102000
0&
#103000
11
1-
b0 !
b0 .
b0 4
b0 9
1&
#104000
0&
#105000
01
1,
0-
b0 $
b0 3
b0 5
b0 6
b1001 !
b1001 .
b1001 4
b1001 9
1&
#106000
0&
#107000
b1000 !
b1000 .
b1000 4
b1000 9
1&
#108000
0&
#109000
b111 !
b111 .
b111 4
b111 9
1&
#110000
0&
#111000
b110 !
b110 .
b110 4
b110 9
1&
#112000
0&
#113000
b101 !
b101 .
b101 4
b101 9
1&
#114000
0&
#115000
b100 !
b100 .
b100 4
b100 9
1&
#116000
0&
#117000
b11 !
b11 .
b11 4
b11 9
1&
#118000
0&
#119000
b10 !
b10 .
b10 4
b10 9
1&
#120000
0&
#121000
b1 !
b1 .
b1 4
b1 9
1&
#122000
0&
#123000
10
11
1-
b0 !
b0 .
b0 4
b0 9
1&
#124000
0&
#125000
00
01
1+
0,
0-
b0 #
b0 2
b0 7
b101 $
b101 3
b101 5
b101 6
b1001 !
b1001 .
b1001 4
b1001 9
1&
#126000
0&
#127000
b1000 !
b1000 .
b1000 4
b1000 9
1&
#128000
0&
#129000
b111 !
b111 .
b111 4
b111 9
1&
#130000
0&
#131000
b110 !
b110 .
b110 4
b110 9
1&
#132000
0&
#133000
b101 !
b101 .
b101 4
b101 9
1&
#134000
0&
#135000
b100 !
b100 .
b100 4
b100 9
1&
#136000
0&
#137000
b11 !
b11 .
b11 4
b11 9
1&
#138000
0&
#139000
b10 !
b10 .
b10 4
b10 9
1&
#140000
0&
#141000
b1 !
b1 .
b1 4
b1 9
1&
#142000
0&
#143000
11
1-
b0 !
b0 .
b0 4
b0 9
1&
#144000
0&
#145000
01
0-
b100 $
b100 3
b100 5
b100 6
b1001 !
b1001 .
b1001 4
b1001 9
1&
#146000
0&
#147000
b1000 !
b1000 .
b1000 4
b1000 9
1&
#148000
0&
#149000
b111 !
b111 .
b111 4
b111 9
1&
#150000
0&
#151000
b110 !
b110 .
b110 4
b110 9
1&
#152000
0&
#153000
b101 !
b101 .
b101 4
b101 9
1&
#154000
0&
#155000
b100 !
b100 .
b100 4
b100 9
1&
#156000
0&
#157000
b11 !
b11 .
b11 4
b11 9
1&
#158000
0&
#159000
b10 !
b10 .
b10 4
b10 9
1&
#160000
0&
#161000
b1 !
b1 .
b1 4
b1 9
1&
#162000
0&
#163000
11
1-
b0 !
b0 .
b0 4
b0 9
1&
#164000
0&
#165000
01
0-
b11 $
b11 3
b11 5
b11 6
b1001 !
b1001 .
b1001 4
b1001 9
1&
#166000
0&
#167000
b1000 !
b1000 .
b1000 4
b1000 9
1&
#168000
0&
#169000
b111 !
b111 .
b111 4
b111 9
1&
#170000
0&
#171000
b110 !
b110 .
b110 4
b110 9
1&
#172000
0&
#173000
b101 !
b101 .
b101 4
b101 9
1&
#174000
0&
#175000
b100 !
b100 .
b100 4
b100 9
1&
#176000
0&
#177000
b11 !
b11 .
b11 4
b11 9
1&
#178000
0&
#179000
b10 !
b10 .
b10 4
b10 9
1&
#180000
0&
#181000
b1 !
b1 .
b1 4
b1 9
1&
#182000
0&
#183000
11
1-
b0 !
b0 .
b0 4
b0 9
1&
#184000
0&
#185000
01
0-
b10 $
b10 3
b10 5
b10 6
b1001 !
b1001 .
b1001 4
b1001 9
1&
#186000
0&
#187000
b1000 !
b1000 .
b1000 4
b1000 9
1&
#188000
0&
#189000
b111 !
b111 .
b111 4
b111 9
1&
#190000
0&
#191000
b110 !
b110 .
b110 4
b110 9
1&
#192000
0&
#193000
b101 !
b101 .
b101 4
b101 9
1&
#194000
0&
#195000
b100 !
b100 .
b100 4
b100 9
1&
#196000
0&
#197000
b11 !
b11 .
b11 4
b11 9
1&
#198000
0&
#199000
b10 !
b10 .
b10 4
b10 9
1&
#200000
0&
#201000
b1 !
b1 .
b1 4
b1 9
1&
#202000
0&
#203000
11
1-
b0 !
b0 .
b0 4
b0 9
1&
#204000
0&
#205000
01
0-
b1 $
b1 3
b1 5
b1 6
b1001 !
b1001 .
b1001 4
b1001 9
1&
#206000
0&
#207000
b1000 !
b1000 .
b1000 4
b1000 9
1&
#208000
0&
#209000
b111 !
b111 .
b111 4
b111 9
1&
#210000
0&
#211000
b110 !
b110 .
b110 4
b110 9
1&
#212000
0&
#213000
b101 !
b101 .
b101 4
b101 9
1&
#214000
0&
#215000
b100 !
b100 .
b100 4
b100 9
1&
#216000
0&
#217000
b11 !
b11 .
b11 4
b11 9
1&
#218000
0&
#219000
b10 !
b10 .
b10 4
b10 9
1&
#220000
0&
#221000
b1 !
b1 .
b1 4
b1 9
1&
#222000
0&
#223000
11
1-
b0 !
b0 .
b0 4
b0 9
1&
#224000
0&
#225000
01
1,
0-
b0 $
b0 3
b0 5
b0 6
b1001 !
b1001 .
b1001 4
b1001 9
1&
#226000
0&
#227000
b1000 !
b1000 .
b1000 4
b1000 9
1&
#228000
0&
#229000
b111 !
b111 .
b111 4
b111 9
1&
#230000
0&
#231000
b110 !
b110 .
b110 4
b110 9
1&
#232000
0&
#233000
b101 !
b101 .
b101 4
b101 9
1&
#234000
0&
#235000
b100 !
b100 .
b100 4
b100 9
1&
#236000
0&
#237000
b11 !
b11 .
b11 4
b11 9
1&
#238000
0&
#239000
b10 !
b10 .
b10 4
b10 9
1&
#240000
0&
#241000
b1 !
b1 .
b1 4
b1 9
1&
#242000
0&
#243000
1/
10
1"
11
1-
b0 !
b0 .
b0 4
b0 9
1&
#244000
0&
#245000
0/
0"
00
01
0+
0,
0-
b1001 #
b1001 2
b1001 7
b101 $
b101 3
b101 5
b101 6
b1001 !
b1001 .
b1001 4
b1001 9
1&
#246000
0&
#247000
b1000 !
b1000 .
b1000 4
b1000 9
1&
#248000
0&
#249000
b111 !
b111 .
b111 4
b111 9
1&
#250000
0&
#251000
b110 !
b110 .
b110 4
b110 9
1&
#252000
0&
#253000
b101 !
b101 .
b101 4
b101 9
1&
#254000
0&
#255000
b100 !
b100 .
b100 4
b100 9
1&
#256000
0&
#257000
b11 !
b11 .
b11 4
b11 9
1&
#258000
0&
#259000
b10 !
b10 .
b10 4
b10 9
1&
#260000
0&
#261000
b1 !
b1 .
b1 4
b1 9
1&
#262000
0&
#263000
11
1-
b0 !
b0 .
b0 4
b0 9
1&
#264000
0&
#265000
01
0-
b100 $
b100 3
b100 5
b100 6
b1001 !
b1001 .
b1001 4
b1001 9
1&
#266000
0&
#267000
b1000 !
b1000 .
b1000 4
b1000 9
1&
#268000
0&
#269000
b111 !
b111 .
b111 4
b111 9
1&
#270000
0&
#271000
b110 !
b110 .
b110 4
b110 9
1&
#272000
0&
#273000
b101 !
b101 .
b101 4
b101 9
1&
#274000
0&
#275000
b100 !
b100 .
b100 4
b100 9
1&
#276000
0&
#277000
b11 !
b11 .
b11 4
b11 9
1&
#278000
0&
#279000
b10 !
b10 .
b10 4
b10 9
1&
#280000
0&
#281000
b1 !
b1 .
b1 4
b1 9
1&
#282000
0&
#283000
11
1-
b0 !
b0 .
b0 4
b0 9
1&
#284000
0&
#285000
01
0-
b11 $
b11 3
b11 5
b11 6
b1001 !
b1001 .
b1001 4
b1001 9
1&
#286000
0&
#287000
b1000 !
b1000 .
b1000 4
b1000 9
1&
#288000
0&
#289000
b111 !
b111 .
b111 4
b111 9
1&
#290000
0&
#291000
b110 !
b110 .
b110 4
b110 9
1&
#292000
0&
#293000
b101 !
b101 .
b101 4
b101 9
1&
#294000
0&
#295000
b100 !
b100 .
b100 4
b100 9
1&
#296000
0&
#297000
b11 !
b11 .
b11 4
b11 9
1&
#298000
0&
#299000
b10 !
b10 .
b10 4
b10 9
1&
#300000
0&
#301000
b1 !
b1 .
b1 4
b1 9
1&
#302000
0&
#303000
11
1-
b0 !
b0 .
b0 4
b0 9
1&
#304000
0&
#305000
01
0-
b10 $
b10 3
b10 5
b10 6
b1001 !
b1001 .
b1001 4
b1001 9
1&
#306000
0&
#307000
b1000 !
b1000 .
b1000 4
b1000 9
1&
#308000
0&
#309000
b111 !
b111 .
b111 4
b111 9
1&
#310000
0&
#311000
b110 !
b110 .
b110 4
b110 9
1&
#312000
0&
#313000
b101 !
b101 .
b101 4
b101 9
1&
#314000
0&
#315000
b100 !
b100 .
b100 4
b100 9
1&
#316000
0&
#317000
b11 !
b11 .
b11 4
b11 9
1&
#318000
0&
#319000
b10 !
b10 .
b10 4
b10 9
1&
#320000
0&
#321000
b1 !
b1 .
b1 4
b1 9
1&
#322000
0&
#323000
11
1-
b0 !
b0 .
b0 4
b0 9
1&
#324000
0&
#325000
01
0-
b1 $
b1 3
b1 5
b1 6
b1001 !
b1001 .
b1001 4
b1001 9
1&
#326000
0&
#327000
b1000 !
b1000 .
b1000 4
b1000 9
1&
#328000
0&
#329000
b111 !
b111 .
b111 4
b111 9
1&
#330000
0&
#331000
b110 !
b110 .
b110 4
b110 9
1&
#332000
0&
#333000
b101 !
b101 .
b101 4
b101 9
1&
#334000
0&
#335000
b100 !
b100 .
b100 4
b100 9
1&
#336000
0&
#337000
b11 !
b11 .
b11 4
b11 9
1&
#338000
0&
#339000
b10 !
b10 .
b10 4
b10 9
1&
#340000
0&
#341000
b1 !
b1 .
b1 4
b1 9
1&
#342000
0&
#343000
11
1-
b0 !
b0 .
b0 4
b0 9
1&
#344000
0&
#345000
01
1,
0-
b0 $
b0 3
b0 5
b0 6
b1001 !
b1001 .
b1001 4
b1001 9
1&
#346000
0&
#347000
b1000 !
b1000 .
b1000 4
b1000 9
1&
#348000
0&
#349000
b111 !
b111 .
b111 4
b111 9
1&
#350000
0&
#351000
b110 !
b110 .
b110 4
b110 9
1&
#352000
0&
#353000
b101 !
b101 .
b101 4
b101 9
1&
#354000
0&
#355000
b100 !
b100 .
b100 4
b100 9
1&
#356000
0&
#357000
b11 !
b11 .
b11 4
b11 9
1&
#358000
0&
#359000
b10 !
b10 .
b10 4
b10 9
1&
#360000
0&
#361000
b1 !
b1 .
b1 4
b1 9
1&
#362000
0&
#363000
10
11
1-
b0 !
b0 .
b0 4
b0 9
1&
#364000
0&
#365000
00
01
0,
0-
b1000 #
b1000 2
b1000 7
b101 $
b101 3
b101 5
b101 6
b1001 !
b1001 .
b1001 4
b1001 9
1&
#366000
0&
#367000
b1000 !
b1000 .
b1000 4
b1000 9
1&
#368000
0&
#369000
b111 !
b111 .
b111 4
b111 9
1&
#370000
0&
#371000
b110 !
b110 .
b110 4
b110 9
1&
#372000
0&
#373000
b101 !
b101 .
b101 4
b101 9
1&
#374000
0&
#375000
b100 !
b100 .
b100 4
b100 9
1&
#376000
0&
#377000
b11 !
b11 .
b11 4
b11 9
1&
#378000
0&
#379000
b10 !
b10 .
b10 4
b10 9
1&
#380000
0&
#381000
b1 !
b1 .
b1 4
b1 9
1&
#382000
0&
#383000
11
1-
b0 !
b0 .
b0 4
b0 9
1&
#384000
0&
#385000
01
0-
b100 $
b100 3
b100 5
b100 6
b1001 !
b1001 .
b1001 4
b1001 9
1&
#386000
0&
#387000
b1000 !
b1000 .
b1000 4
b1000 9
1&
#388000
0&
#389000
b111 !
b111 .
b111 4
b111 9
1&
#390000
0&
#391000
b110 !
b110 .
b110 4
b110 9
1&
#392000
0&
#393000
b101 !
b101 .
b101 4
b101 9
1&
#394000
0&
#395000
b100 !
b100 .
b100 4
b100 9
1&
#396000
0&
#397000
b11 !
b11 .
b11 4
b11 9
1&
#398000
0&
#399000
b10 !
b10 .
b10 4
b10 9
1&
#400000
0&
#401000
b1 !
b1 .
b1 4
b1 9
1&
#402000
0&
#403000
11
1-
b0 !
b0 .
b0 4
b0 9
1&
#404000
0&
#405000
01
0-
b11 $
b11 3
b11 5
b11 6
b1001 !
b1001 .
b1001 4
b1001 9
1&
#406000
0&
#407000
b1000 !
b1000 .
b1000 4
b1000 9
1&
#408000
0&
#409000
b111 !
b111 .
b111 4
b111 9
1&
#410000
0&
#411000
b110 !
b110 .
b110 4
b110 9
1&
#412000
0&
#413000
b101 !
b101 .
b101 4
b101 9
1&
#414000
0&
#415000
b100 !
b100 .
b100 4
b100 9
1&
#416000
0&
#417000
b11 !
b11 .
b11 4
b11 9
1&
#418000
0&
#419000
b10 !
b10 .
b10 4
b10 9
1&
#420000
0&
#421000
b1 !
b1 .
b1 4
b1 9
1&
#422000
0&
#423000
11
1-
b0 !
b0 .
b0 4
b0 9
1&
#424000
0&
#425000
01
0-
b10 $
b10 3
b10 5
b10 6
b1001 !
b1001 .
b1001 4
b1001 9
1&
#426000
0&
#427000
b1000 !
b1000 .
b1000 4
b1000 9
1&
#428000
0&
#429000
b111 !
b111 .
b111 4
b111 9
1&
#430000
0&
#431000
b110 !
b110 .
b110 4
b110 9
1&
#432000
0&
#433000
b101 !
b101 .
b101 4
b101 9
1&
#434000
0&
#435000
b100 !
b100 .
b100 4
b100 9
1&
#436000
0&
#437000
b11 !
b11 .
b11 4
b11 9
1&
#438000
0&
#439000
b10 !
b10 .
b10 4
b10 9
1&
#440000
0&
#441000
b1 !
b1 .
b1 4
b1 9
1&
#442000
0&
#443000
11
1-
b0 !
b0 .
b0 4
b0 9
1&
#444000
0&
#445000
01
0-
b1 $
b1 3
b1 5
b1 6
b1001 !
b1001 .
b1001 4
b1001 9
1&
#446000
0&
#447000
b1000 !
b1000 .
b1000 4
b1000 9
1&
#448000
0&
#449000
b111 !
b111 .
b111 4
b111 9
1&
#450000
0&
#451000
b110 !
b110 .
b110 4
b110 9
1&
#452000
0&
#453000
b101 !
b101 .
b101 4
b101 9
1&
#454000
0&
#455000
b100 !
b100 .
b100 4
b100 9
1&
#456000
0&
#457000
b11 !
b11 .
b11 4
b11 9
1&
#458000
0&
#459000
b10 !
b10 .
b10 4
b10 9
1&
#460000
0&
#461000
b1 !
b1 .
b1 4
b1 9
1&
#462000
0&
#463000
11
1-
b0 !
b0 .
b0 4
b0 9
1&
#464000
0&
#465000
01
1,
0-
b0 $
b0 3
b0 5
b0 6
b1001 !
b1001 .
b1001 4
b1001 9
1&
#466000
0&
#467000
b1000 !
b1000 .
b1000 4
b1000 9
1&
#468000
0&
#469000
b111 !
b111 .
b111 4
b111 9
1&
#470000
0&
#471000
b110 !
b110 .
b110 4
b110 9
1&
#472000
0&
#473000
b101 !
b101 .
b101 4
b101 9
1&
#474000
0&
#475000
b100 !
b100 .
b100 4
b100 9
1&
#476000
0&
#477000
b11 !
b11 .
b11 4
b11 9
1&
#478000
0&
#479000
b10 !
b10 .
b10 4
b10 9
1&
#480000
0&
#481000
b1 !
b1 .
b1 4
b1 9
1&
#482000
0&
#483000
10
11
1-
b0 !
b0 .
b0 4
b0 9
1&
#484000
0&
#485000
00
01
0,
0-
b111 #
b111 2
b111 7
b101 $
b101 3
b101 5
b101 6
b1001 !
b1001 .
b1001 4
b1001 9
1&
#486000
0&
#487000
b1000 !
b1000 .
b1000 4
b1000 9
1&
#488000
0&
#489000
b111 !
b111 .
b111 4
b111 9
1&
#490000
0&
#491000
b110 !
b110 .
b110 4
b110 9
1&
#492000
0&
#493000
b101 !
b101 .
b101 4
b101 9
1&
#494000
0&
#495000
b100 !
b100 .
b100 4
b100 9
1&
#496000
0&
#497000
b11 !
b11 .
b11 4
b11 9
1&
#498000
0&
#499000
b10 !
b10 .
b10 4
b10 9
1&
#500000
0&
#501000
b1 !
b1 .
b1 4
b1 9
1&
#502000
0&
#503000
11
1-
b0 !
b0 .
b0 4
b0 9
1&
#504000
0&
#505000
01
0-
b100 $
b100 3
b100 5
b100 6
b1001 !
b1001 .
b1001 4
b1001 9
1&
#506000
0&
#507000
b1000 !
b1000 .
b1000 4
b1000 9
1&
#508000
0&
#509000
b111 !
b111 .
b111 4
b111 9
1&
#510000
0&
#511000
b110 !
b110 .
b110 4
b110 9
1&
#512000
0&
#513000
b101 !
b101 .
b101 4
b101 9
1&
#514000
0&
#515000
b100 !
b100 .
b100 4
b100 9
1&
#516000
0&
#517000
b11 !
b11 .
b11 4
b11 9
1&
#518000
0&
#519000
b10 !
b10 .
b10 4
b10 9
1&
#520000
0&
#521000
b1 !
b1 .
b1 4
b1 9
1&
#522000
0&
#523000
11
1-
b0 !
b0 .
b0 4
b0 9
1&
#524000
0&
#525000
01
0-
b11 $
b11 3
b11 5
b11 6
b1001 !
b1001 .
b1001 4
b1001 9
1&
#526000
0&
#527000
b1000 !
b1000 .
b1000 4
b1000 9
1&
#528000
0&
#529000
b111 !
b111 .
b111 4
b111 9
1&
#530000
0&
#531000
b110 !
b110 .
b110 4
b110 9
1&
#532000
0&
#533000
b101 !
b101 .
b101 4
b101 9
1&
#534000
0&
#535000
b100 !
b100 .
b100 4
b100 9
1&
#536000
0&
#537000
b11 !
b11 .
b11 4
b11 9
1&
#538000
0&
#539000
b10 !
b10 .
b10 4
b10 9
1&
#540000
0&
#541000
b1 !
b1 .
b1 4
b1 9
1&
#542000
0&
#543000
11
1-
b0 !
b0 .
b0 4
b0 9
1&
#544000
0&
#545000
01
0-
b10 $
b10 3
b10 5
b10 6
b1001 !
b1001 .
b1001 4
b1001 9
1&
#546000
0&
#547000
b1000 !
b1000 .
b1000 4
b1000 9
1&
#548000
0&
#549000
b111 !
b111 .
b111 4
b111 9
1&
#550000
0&
#551000
b110 !
b110 .
b110 4
b110 9
1&
#552000
0&
#553000
b101 !
b101 .
b101 4
b101 9
1&
#554000
0&
#555000
b100 !
b100 .
b100 4
b100 9
1&
#556000
0&
#557000
b11 !
b11 .
b11 4
b11 9
1&
#558000
0&
#559000
b10 !
b10 .
b10 4
b10 9
1&
#560000
0&
#561000
b1 !
b1 .
b1 4
b1 9
1&
#562000
0&
#563000
11
1-
b0 !
b0 .
b0 4
b0 9
1&
#564000
0&
#565000
01
0-
b1 $
b1 3
b1 5
b1 6
b1001 !
b1001 .
b1001 4
b1001 9
1&
#566000
0&
#567000
b1000 !
b1000 .
b1000 4
b1000 9
1&
#568000
0&
#569000
b111 !
b111 .
b111 4
b111 9
1&
#570000
0&
#571000
b110 !
b110 .
b110 4
b110 9
1&
#572000
0&
#573000
b101 !
b101 .
b101 4
b101 9
1&
#574000
0&
#575000
b100 !
b100 .
b100 4
b100 9
1&
#576000
0&
#577000
b11 !
b11 .
b11 4
b11 9
1&
#578000
0&
#579000
b10 !
b10 .
b10 4
b10 9
1&
#580000
0&
#581000
b1 !
b1 .
b1 4
b1 9
1&
#582000
0&
#583000
11
1-
b0 !
b0 .
b0 4
b0 9
1&
#584000
0&
#585000
01
1,
0-
b0 $
b0 3
b0 5
b0 6
b1001 !
b1001 .
b1001 4
b1001 9
1&
#586000
0&
