nivel1/nivel2/entrada_timer_controle/encoder/encoder.v
module encoder(
    input wire [9:0] keyboard,
    input wire enablen,
    output reg [3:0] bcd,
    output reg valid_data
);

    always @(keyboard)
        if (enablen == 1'b0) begin
            case(keyboard)
                10'b1000000000: bcd = 4'b1001;
                10'b0100000000: bcd = 4'b1000;
                10'b0010000000: bcd = 4'b0111;
                10'b0001000000: bcd = 4'b0110;
                10'b0000100000: bcd = 4'b0101;
                10'b0000010000: bcd = 4'b0100;
                10'b0000001000: bcd = 4'b0011;
                10'b0000000100: bcd = 4'b0010;
                10'b0000000010: bcd = 4'b0001;
                10'b0000000001: bcd = 4'b0000;
            endcase
            valid_data = 1'b1;
        end

        else begin
            valid_data = 1'b0;
        end

endmodule

nivel1/nivel2/entrada_timer_controle/encoder/encoder_tb.v
`timescale 1ns/1ns
`include "encoder.v"

module encoder_tb;

    reg [9:0]keyboard_tb;
    reg enablen_tb;
  	wire valid_data_tb;
    wire [3:0]bcd_tb;

  	encoder dut(
        .keyboard(keyboard_tb), .enablen(enablen_tb), 
        .bcd(bcd_tb), .valid_data(valid_data_tb)
    );

    initial begin

        $dumpfile("encoder_tb.vcd");
        $dumpvars(0, encoder_tb);

        keyboard_tb=10'b1000000000; enablen_tb=0;
        #5 keyboard_tb=10'b0100000000; enablen_tb=0; 
        #5 keyboard_tb=10'b0010000000; enablen_tb=0;
        #5 keyboard_tb=10'b0001000000; enablen_tb=0;
        #5 keyboard_tb=10'b0000100000; enablen_tb=0;
        #5 keyboard_tb=10'b0000010000; enablen_tb=0;
        #5 keyboard_tb=10'b0000001000; enablen_tb=0;
        #5 keyboard_tb=10'b0000000100; enablen_tb=0;
        #5 keyboard_tb=10'b0000000010; enablen_tb=0;
        #5 keyboard_tb=10'b0000000001; enablen_tb=0;

        #5 keyboard_tb=10'b1000000000; enablen_tb=1;
        #5 keyboard_tb=10'b0100000000; enablen_tb=1; 
        #5 keyboard_tb=10'b0010000000; enablen_tb=1;
        #5 keyboard_tb=10'b0001000000; enablen_tb=1;
        #5 keyboard_tb=10'b0000100000; enablen_tb=1;
        #5 keyboard_tb=10'b0000010000; enablen_tb=1;
        #5 keyboard_tb=10'b0000001000; enablen_tb=1;
        #5 keyboard_tb=10'b0000000100; enablen_tb=1;
        #5 keyboard_tb=10'b0000000010; enablen_tb=1;
        #5 keyboard_tb=10'b0000000001; enablen_tb=1;

        #5 keyboard_tb=10'b1000000001; enablen_tb=0;
        #5 keyboard_tb=10'b1000001001; enablen_tb=0;
        #5 keyboard_tb=10'b1000000001; enablen_tb=1;
        #5 keyboard_tb=10'b1000001001; enablen_tb=1;

          
    end
endmodule

nivel1/nivel2/entrada_timer_controle/encoder/encoder_tb.vcd
$date
	Sat Apr 22 23:07:56 2023
$end
$version
	Icarus Verilog
$end
$timescale
	1ns
$end
$scope module encoder_tb $end
$var wire 1 ! valid_data_tb $end
$var wire 4 " bcd_tb [3:0] $end
$var reg 1 # enablen_tb $end
$var reg 10 $ keyboard_tb [9:0] $end
$scope module dut $end
$var wire 1 # enablen $end
$var wire 10 % keyboard [9:0] $end
$var reg 4 & bcd [3:0] $end
$var reg 1 ! valid_data $end
$upscope $end
$upscope $end
$enddefinitions $end
#0
$dumpvars
b1001 &
b1000000000 %
b1000000000 $
0#
b1001 "
1!
$end
#5
b1000 "
b1000 &
b100000000 $
b100000000 %
#10
b111 "
b111 &
b10000000 $
b10000000 %
#15
b110 "
b110 &
b1000000 $
b1000000 %
#20
b101 "
b101 &
b100000 $
b100000 %
#25
b100 "
b100 &
b10000 $
b10000 %
#30
b11 "
b11 &
b1000 $
b1000 %
#35
b10 "
b10 &
b100 $
b100 %
#40
b1 "
b1 &
b10 $
b10 %
#45
b0 "
b0 &
b1 $
b1 %
#50
0!
1#
b1000000000 $
b1000000000 %
#55
b100000000 $
b100000000 %
#60
b10000000 $
b10000000 %
#65
b1000000 $
b1000000 %
#70
b100000 $
b100000 %
#75
b10000 $
b10000 %
#80
b1000 $
b1000 %
#85
b100 $
b100 %
#90
b10 $
b10 %
#95
b1 $
b1 %
#100
1!
0#
b1000000001 $
b1000000001 %
#105
b1000001001 $
b1000001001 %
#110
0!
1#
b1000000001 $
b1000000001 %
#115
b1000001001 $
b1000001001 %
