nivel1/nivel2/timer_min_sec/nivel3_timer/contador_mod10_2.v
`timescale 1ns/1ps

module contador_mod10_2 (
    input wire clk,          // sinal de clock
    input wire loadn,        
  	input wire [3:0] data,   // valor inicial do contador
    input wire clearn,       // sinal de reset em nível baixo
    input wire en,           // sinal de habilitação em nível alto
    output wire tc,
    output wire zero,
  	output reg [3:0] mins // saída do contador
);

  assign zero = (mins == 4'b0000) ? 1'b1 : 1'b0;
  assign tc = en & zero;

  always @(posedge clk) begin
    if (~loadn) begin
        mins <= data; // reinicia o contador com o valor de 'data'
    end else if (~clearn) begin
        mins <= 3'b000; // zera o contador quando 'clearn' está em nível baixo
    end else if (en) begin
        if (mins == 4'b0000) begin
            mins <= 4'b1001; // volta a contar a partir de 9 quando atinge 0
        end else begin
            mins <= mins - 1; // subtrai 1 do contador
        end
    end
  end

endmodule

nivel1/nivel2/timer_min_sec/nivel3_timer/contador_mod6.v

module contador_mod6 (
    input wire clk,          // sinal de clock
    input loadn,        
  	input wire [3:0] data,   // valor inicial do contador
    input clearn,       // sinal de reset em nível baixo
    input en,           // sinal de habilitação em nível alto
    output wire tc,
    output wire zero,
  	output reg [3:0] tens // saída do contador
);
  always @ (negedge clearn) // lembrar de trocar o reset e o stop (feito)
  begin
    tens = 4'b0000;
  end
  assign zero = (tens == 4'b0000) ? 1'b1 : 1'b0;
  assign tc = en & zero;

  always @(posedge clk) begin
    if (en)
        if (tens == 4'b0000) begin
            tens <= 4'b0101; // volta a contar a partir de 5 quando atinge 0
        end else 
            tens <= tens - 4'b0001; // subtrai 1 do contador
        
    else begin
      if (~loadn)
          tens <= data; // reinicia o contador com o valor de 'data'
    end
  end

endmodule

nivel1/nivel2/timer_min_sec/nivel3_timer/contador_mod10.v
`timescale 1ns/1ps

module contador_mod10 (
    input wire clk,          // sinal de clock
    input loadn,        
  	input wire [3:0] data,   // valor inicial do contador
    input clearn,       // sinal de reset em nível baixo
    input en,           // sinal de habilitação em nível alto
    output wire tc,
    output wire zero,
  	output reg [3:0] ones // saída do contador
);
always @ (negedge clearn) // Lembrar de trocar o reset e o stop (feito)
  begin
    ones = 4'b0000;
  end
  assign zero = (ones == 4'b0000) ? 1'b1 : 1'b0;
  assign tc = en & zero;

  always @(posedge clk) begin
    if (en) 
        if (ones == 4'b0000) begin
            ones <= 4'b1001; // volta a contar a partir de 9 quando atinge 0
        end else
            ones <= ones - 4'b0001; // subtrai 1 do contador
        
    else begin
      if (~loadn)
          ones <= data; // reinicia o contador com o valor de 'data'
    end
  end

endmodule

nivel1/nivel2/timer_min_sec/timer_nivel2.v
// Importando os módulos dos contadores
`include "nivel3_timer/contador_mod10.v"
`include "nivel3_timer/contador_mod6.v"
`include "nivel3_timer/contador_mod10_2.v"

// Definindo a escala de tempo do módulo
`timescale 1ns/1ps

// Definindo o módulo timer_nivel2
module timer_nivel2(data, clk, enable, load, clear, unidades, dezenas, minutos, zero);

  // Definindo as entradas do módulo
  input [3:0] data;
  input wire clk, enable, load, clear; // Lembrar que aqui tudo menos o clk está invertido (load equivale a loadn...)
  
  // Definindo as saídas do módulo
  output wire [3:0] unidades, dezenas, minutos;
  output wire zero;
  
  // Definindo os sinais de controle dos contadores
  wire tc1;
  wire tc2;
  wire tc3;
  
  // Definindo os sinais de saída de zero dos contadores
  wire zero1;
  wire zero2;
  wire zero3;

  // Instanciando o contador_mod10 para as unidades
  contador_mod10 unidade(clk, load, data, clear, enable, tc1, zero1, unidades);
  
  // Instanciando o contador_mod6 para as dezenas
  contador_mod6 dezena(clk, load, unidades, clear, tc1, tc2, zero2, dezenas);
  
  // Instanciando o contador_mod10 para os minutos
  contador_mod10_2 minuto(clk, load, dezenas, clear, tc2, tc3, zero3, minutos);

  // Definindo o sinal zero como o AND das saídas zero dos contadores
  assign zero = zero1 & zero2 & zero3;
endmodule

nivel1/nivel2/timer_min_sec/timer_nivel2_tb.v
`timescale 1ns/1ps
`include "timer_nivel2.v"

module timer_nivel2_tb();
  // Declaração de entradas e saídas do testbench
    wire[3:0] minutos_tb, dezenas, unidades_tb;
    wire contador_zerado;
    reg [3:0]  data_tb;
    reg clearn_tb, enable_tb, loadn_tb, clk_tb;

    // Instanciando o DUT (Device Under Test) e suas conexões
    timer_nivel2 DUT(data_tb, clk_tb, enable_tb, loadn_tb, clearn_tb,
                  unidades_tb, dezenas, minutos_tb, contador_zerado);

    initial begin
        $dumpfile("timer_nivel2_tb.vcd"); // Define o nome do arquivo de simulação
        $dumpvars(0,timer_nivel2_tb); // Define quais variáveis serão salvas no arquivo de simulação
        clk_tb  = 1'b0; // Inicializa o clock
        enable_tb = 1'b0; // Desabilita o timer
        loadn_tb  = 1'b0; // Desativa o sinal de carregamento
    end

    always begin
        #1 clk_tb = loadn_tb? ~clk_tb : clk_tb; // Gera o sinal de clock
    end

    initial begin    
        clearn_tb = 1'b1; #0.5 // Ativa o sinal de limpeza por 0.5ns
        clearn_tb = 1'b0; #0.5 // Desativa o sinal de limpeza por 0.5ns
        clearn_tb = 1'b1; #0.5 // Ativa novamente o sinal de limpeza por 0.5ns

        data_tb =  2;   #0.04; // Define o valor de entrada para 2 e espera 0.04ns
        clk_tb = 1'b1;   #0.01; // Gera uma borda de subida no clock por 0.01ns
        clk_tb = 1'b0;   #0.95; // Gera uma borda de descida no clock por 0.95ns

        data_tb =  0;   #0.04; // Define o valor de entrada para 0 e espera 0.04ns
        clk_tb = 1'b1;   #0.01; // Gera uma borda de subida no clock por 0.01ns
        clk_tb = 1'b0;   #0.95; // Gera uma borda de descida no clock por 0.95ns

        data_tb =  0;   #0.04; // Define o valor de entrada para 0 e espera 0.04ns
        clk_tb = 1'b1;   #0.01; // Gera uma borda de subida no clock por 0.01ns
        clk_tb = 1'b0;   #0.95; // Gera uma borda de descida no clock por 0.95ns
        enable_tb = 1; loadn_tb = 1; #240.5; // Habilita o timer e ativa o sinal de carregamento por 240.5ns
        
        $finish();
    end
endmodule

nivel1/nivel2/timer_min_sec/timer_nivel2_tb.vcd
$date
	Sat Apr 22 21:21:01 2023
$end
$version
	Icarus Verilog
$end
$timescale
	1ps
$end
$scope module timer_nivel2_tb $end
$var wire 4 ! unidades_tb [3:0] $end
$var wire 4 " minutos_tb [3:0] $end
$var wire 4 # dezenas [3:0] $end
$var wire 1 $ contador_zerado $end
$var reg 1 % clearn_tb $end
$var reg 1 & clk_tb $end
$var reg 4 ' data_tb [3:0] $end
$var reg 1 ( enable_tb $end
$var reg 1 ) loadn_tb $end
$scope module DUT $end
$var wire 1 % clear $end
$var wire 1 & clk $end
$var wire 4 * data [3:0] $end
$var wire 1 ( enable $end
$var wire 1 ) load $end
$var wire 1 $ zero $end
$var wire 1 + zero3 $end
$var wire 1 , zero2 $end
$var wire 1 - zero1 $end
$var wire 4 . unidades [3:0] $end
$var wire 1 / tc3 $end
$var wire 1 0 tc2 $end
$var wire 1 1 tc1 $end
$var wire 4 2 minutos [3:0] $end
$var wire 4 3 dezenas [3:0] $end
$scope module dezena $end
$var wire 1 % clearn $end
$var wire 1 & clk $end
$var wire 1 ) loadn $end
$var wire 1 0 tc $end
$var wire 1 , zero $end
$var wire 1 1 en $end
$var wire 4 4 data [3:0] $end
$var reg 4 5 tens [3:0] $end
$upscope $end
$scope module minuto $end
$var wire 1 % clearn $end
$var wire 1 & clk $end
$var wire 4 6 data [3:0] $end
$var wire 1 0 en $end
$var wire 1 ) loadn $end
$var wire 1 / tc $end
$var wire 1 + zero $end
$var reg 4 7 mins [3:0] $end
$upscope $end
$scope module unidade $end
$var wire 1 % clearn $end
$var wire 1 & clk $end
$var wire 4 8 data [3:0] $end
$var wire 1 ( en $end
$var wire 1 ) loadn $end
$var wire 1 1 tc $end
$var wire 1 - zero $end
$var reg 4 9 ones [3:0] $end
$upscope $end
$upscope $end
$upscope $end
$enddefinitions $end
$comment Show the parameter values. $end
$dumpall
$end
#0
$dumpvars
bx 9
bx 8
bx 7
bx 6
bx 5
bx 4
bx 3
bx 2
01
00
0/
bx .
x-
x,
x+
bx *
0)
0(
bx '
0&
1%
x$
bx #
bx "
bx !
$end
#500
0%
#1000
1%
#1500
b10 '
b10 *
b10 8
#1540
0$
0-
b10 !
b10 .
b10 4
b10 9
1&
#1550
0&
#2500
b0 '
b0 *
b0 8
#2540
0,
1-
b10 #
b10 3
b10 5
b10 6
b0 !
b0 .
b0 4
b0 9
1&
#2550
0&
#3540
1,
0+
b0 #
b0 3
b0 5
b0 6
b10 "
b10 2
b10 7
1&
#3550
0&
#4500
10
11
1)
1(
#5000
00
01
0,
0-
b1 "
b1 2
b1 7
b101 #
b101 3
b101 5
b101 6
b1001 !
b1001 .
b1001 4
b1001 9
1&
#6000
0&
#7000
b1000 !
b1000 .
b1000 4
b1000 9
1&
#8000
0&
#9000
b111 !
b111 .
b111 4
b111 9
1&
#10000
0&
#11000
b110 !
b110 .
b110 4
b110 9
1&
#12000
0&
#13000
b101 !
b101 .
b101 4
b101 9
1&
#14000
0&
#15000
b100 !
b100 .
b100 4
b100 9
1&
#16000
0&
#17000
b11 !
b11 .
b11 4
b11 9
1&
#18000
0&
#19000
b10 !
b10 .
b10 4
b10 9
1&
#20000
0&
#21000
b1 !
b1 .
b1 4
b1 9
1&
#22000
0&
#23000
11
1-
b0 !
b0 .
b0 4
b0 9
1&
#24000
0&
#25000
01
0-
b100 #
b100 3
b100 5
b100 6
b1001 !
b1001 .
b1001 4
b1001 9
1&
#26000
0&
#27000
b1000 !
b1000 .
b1000 4
b1000 9
1&
#28000
0&
#29000
b111 !
b111 .
b111 4
b111 9
1&
#30000
0&
#31000
b110 !
b110 .
b110 4
b110 9
1&
#32000
0&
#33000
b101 !
b101 .
b101 4
b101 9
1&
#34000
0&
#35000
b100 !
b100 .
b100 4
b100 9
1&
#36000
0&
#37000
b11 !
b11 .
b11 4
b11 9
1&
#38000
0&
#39000
b10 !
b10 .
b10 4
b10 9
1&
#40000
0&
#41000
b1 !
b1 .
b1 4
b1 9
1&
#42000
0&
#43000
11
1-
b0 !
b0 .
b0 4
b0 9
1&
#44000
0&
#45000
01
0-
b11 #
b11 3
b11 5
b11 6
b1001 !
b1001 .
b1001 4
b1001 9
1&
#46000
0&
#47000
b1000 !
b1000 .
b1000 4
b1000 9
1&
#48000
0&
#49000
b111 !
b111 .
b111 4
b111 9
1&
#50000
0&
#51000
b110 !
b110 .
b110 4
b110 9
1&
#52000
0&
#53000
b101 !
b101 .
b101 4
b101 9
1&
#54000
0&
#55000
b100 !
b100 .
b100 4
b100 9
1&
#56000
0&
#57000
b11 !
b11 .
b11 4
b11 9
1&
#58000
0&
#59000
b10 !
b10 .
b10 4
b10 9
1&
#60000
0&
#61000
b1 !
b1 .
b1 4
b1 9
1&
#62000
0&
#63000
11
1-
b0 !
b0 .
b0 4
b0 9
1&
#64000
0&
#65000
01
0-
b10 #
b10 3
b10 5
b10 6
b1001 !
b1001 .
b1001 4
b1001 9
1&
#66000
0&
#67000
b1000 !
b1000 .
b1000 4
b1000 9
1&
#68000
0&
#69000
b111 !
b111 .
b111 4
b111 9
1&
#70000
0&
#71000
b110 !
b110 .
b110 4
b110 9
1&
#72000
0&
#73000
b101 !
b101 .
b101 4
b101 9
1&
#74000
0&
#75000
b100 !
b100 .
b100 4
b100 9
1&
#76000
0&
#77000
b11 !
b11 .
b11 4
b11 9
1&
#78000
0&
#79000
b10 !
b10 .
b10 4
b10 9
1&
#80000
0&
#81000
b1 !
b1 .
b1 4
b1 9
1&
#82000
0&
#83000
11
1-
b0 !
b0 .
b0 4
b0 9
1&
#84000
0&
#85000
01
0-
b1 #
b1 3
b1 5
b1 6
b1001 !
b1001 .
b1001 4
b1001 9
1&
#86000
0&
#87000
b1000 !
b1000 .
b1000 4
b1000 9
1&
#88000
0&
#89000
b111 !
b111 .
b111 4
b111 9
1&
#90000
0&
#91000
b110 !
b110 .
b110 4
b110 9
1&
#92000
0&
#93000
b101 !
b101 .
b101 4
b101 9
1&
#94000
0&
#95000
b100 !
b100 .
b100 4
b100 9
1&
#96000
0&
#97000
b11 !
b11 .
b11 4
b11 9
1&
#98000
0&
#99000
b10 !
b10 .
b10 4
b10 9
1&
#100000
0&
#101000
b1 !
b1 .
b1 4
b1 9
1&
#102000
0&
#103000
11
1-
b0 !
b0 .
b0 4
b0 9
1&
#104000
0&
#105000
01
1,
0-
b0 #
b0 3
b0 5
b0 6
b1001 !
b1001 .
b1001 4
b1001 9
1&
#106000
0&
#107000
b1000 !
b1000 .
b1000 4
b1000 9
1&
#108000
0&
#109000
b111 !
b111 .
b111 4
b111 9
1&
#110000
0&
#111000
b110 !
b110 .
b110 4
b110 9
1&
#112000
0&
#113000
b101 !
b101 .
b101 4
b101 9
1&
#114000
0&
#115000
b100 !
b100 .
b100 4
b100 9
1&
#116000
0&
#117000
b11 !
b11 .
b11 4
b11 9
1&
#118000
0&
#119000
b10 !
b10 .
b10 4
b10 9
1&
#120000
0&
#121000
b1 !
b1 .
b1 4
b1 9
1&
#122000
0&
#123000
10
11
1-
b0 !
b0 .
b0 4
b0 9
1&
#124000
0&
#125000
00
01
1+
0,
0-
b0 "
b0 2
b0 7
b101 #
b101 3
b101 5
b101 6
b1001 !
b1001 .
b1001 4
b1001 9
1&
#126000
0&
#127000
b1000 !
b1000 .
b1000 4
b1000 9
1&
#128000
0&
#129000
b111 !
b111 .
b111 4
b111 9
1&
#130000
0&
#131000
b110 !
b110 .
b110 4
b110 9
1&
#132000
0&
#133000
b101 !
b101 .
b101 4
b101 9
1&
#134000
0&
#135000
b100 !
b100 .
b100 4
b100 9
1&
#136000
0&
#137000
b11 !
b11 .
b11 4
b11 9
1&
#138000
0&
#139000
b10 !
b10 .
b10 4
b10 9
1&
#140000
0&
#141000
b1 !
b1 .
b1 4
b1 9
1&
#142000
0&
#143000
11
1-
b0 !
b0 .
b0 4
b0 9
1&
#144000
0&
#145000
01
0-
b100 #
b100 3
b100 5
b100 6
b1001 !
b1001 .
b1001 4
b1001 9
1&
#146000
0&
#147000
b1000 !
b1000 .
b1000 4
b1000 9
1&
#148000
0&
#149000
b111 !
b111 .
b111 4
b111 9
1&
#150000
0&
#151000
b110 !
b110 .
b110 4
b110 9
1&
#152000
0&
#153000
b101 !
b101 .
b101 4
b101 9
1&
#154000
0&
#155000
b100 !
b100 .
b100 4
b100 9
1&
#156000
0&
#157000
b11 !
b11 .
b11 4
b11 9
1&
#158000
0&
#159000
b10 !
b10 .
b10 4
b10 9
1&
#160000
0&
#161000
b1 !
b1 .
b1 4
b1 9
1&
#162000
0&
#163000
11
1-
b0 !
b0 .
b0 4
b0 9
1&
#164000
0&
#165000
01
0-
b11 #
b11 3
b11 5
b11 6
b1001 !
b1001 .
b1001 4
b1001 9
1&
#166000
0&
#167000
b1000 !
b1000 .
b1000 4
b1000 9
1&
#168000
0&
#169000
b111 !
b111 .
b111 4
b111 9
1&
#170000
0&
#171000
b110 !
b110 .
b110 4
b110 9
1&
#172000
0&
#173000
b101 !
b101 .
b101 4
b101 9
1&
#174000
0&
#175000
b100 !
b100 .
b100 4
b100 9
1&
#176000
0&
#177000
b11 !
b11 .
b11 4
b11 9
1&
#178000
0&
#179000
b10 !
b10 .
b10 4
b10 9
1&
#180000
0&
#181000
b1 !
b1 .
b1 4
b1 9
1&
#182000
0&
#183000
11
1-
b0 !
b0 .
b0 4
b0 9
1&
#184000
0&
#185000
01
0-
b10 #
b10 3
b10 5
b10 6
b1001 !
b1001 .
b1001 4
b1001 9
1&
#186000
0&
#187000
b1000 !
b1000 .
b1000 4
b1000 9
1&
#188000
0&
#189000
b111 !
b111 .
b111 4
b111 9
1&
#190000
0&
#191000
b110 !
b110 .
b110 4
b110 9
1&
#192000
0&
#193000
b101 !
b101 .
b101 4
b101 9
1&
#194000
0&
#195000
b100 !
b100 .
b100 4
b100 9
1&
#196000
0&
#197000
b11 !
b11 .
b11 4
b11 9
1&
#198000
0&
#199000
b10 !
b10 .
b10 4
b10 9
1&
#200000
0&
#201000
b1 !
b1 .
b1 4
b1 9
1&
#202000
0&
#203000
11
1-
b0 !
b0 .
b0 4
b0 9
1&
#204000
0&
#205000
01
0-
b1 #
b1 3
b1 5
b1 6
b1001 !
b1001 .
b1001 4
b1001 9
1&
#206000
0&
#207000
b1000 !
b1000 .
b1000 4
b1000 9
1&
#208000
0&
#209000
b111 !
b111 .
b111 4
b111 9
1&
#210000
0&
#211000
b110 !
b110 .
b110 4
b110 9
1&
#212000
0&
#213000
b101 !
b101 .
b101 4
b101 9
1&
#214000
0&
#215000
b100 !
b100 .
b100 4
b100 9
1&
#216000
0&
#217000
b11 !
b11 .
b11 4
b11 9
1&
#218000
0&
#219000
b10 !
b10 .
b10 4
b10 9
1&
#220000
0&
#221000
b1 !
b1 .
b1 4
b1 9
1&
#222000
0&
#223000
11
1-
b0 !
b0 .
b0 4
b0 9
1&
#224000
0&
#225000
01
1,
0-
b0 #
b0 3
b0 5
b0 6
b1001 !
b1001 .
b1001 4
b1001 9
1&
#226000
0&
#227000
b1000 !
b1000 .
b1000 4
b1000 9
1&
#228000
0&
#229000
b111 !
b111 .
b111 4
b111 9
1&
#230000
0&
#231000
b110 !
b110 .
b110 4
b110 9
1&
#232000
0&
#233000
b101 !
b101 .
b101 4
b101 9
1&
#234000
0&
#235000
b100 !
b100 .
b100 4
b100 9
1&
#236000
0&
#237000
b11 !
b11 .
b11 4
b11 9
1&
#238000
0&
#239000
b10 !
b10 .
b10 4
b10 9
1&
#240000
0&
#241000
b1 !
b1 .
b1 4
b1 9
1&
#242000
0&
#243000
1/
10
1$
11
1-
b0 !
b0 .
b0 4
b0 9
1&
#244000
0&
#245000
0/
0$
00
01
0+
0,
0-
b1001 "
b1001 2
b1001 7
b101 #
b101 3
b101 5
b101 6
b1001 !
b1001 .
b1001 4
b1001 9
1&
