nivel2/decoder/decoder.v
module decoder (output reg [6:0] OutMinutos, OutDezenaSegundos, OutUnidadeSegundos, 
                input wire [3:0] Minutos, DezenaSegundos, UnidadeSegundos);

        always@(Minutos) 
                case(Minutos)
                4'b0000 : OutMinutos = 7'b0000001;
                4'b0001 : OutMinutos = 7'b1001111;
                4'b0010 : OutMinutos = 7'b0010010;
                4'b0011 : OutMinutos = 7'b0000110;
                4'b0100 : OutMinutos = 7'b1001100;
                4'b0101 : OutMinutos = 7'b0100100;
                4'b0110 : OutMinutos = 7'b0100000;
                4'b0111 : OutMinutos = 7'b0001101;
                4'b1000 : OutMinutos = 7'b0000000;
                4'b1001 : OutMinutos = 7'b0000100;
                endcase

        always@(DezenaSegundos)
                case(DezenaSegundos)
                4'b0000 : OutDezenaSegundos = 7'b0000001;
                4'b0001 : OutDezenaSegundos = 7'b1001111;
                4'b0010 : OutDezenaSegundos = 7'b0010010;
                4'b0011 : OutDezenaSegundos = 7'b0000110;
                4'b0100 : OutDezenaSegundos = 7'b1001100;
                4'b0101 : OutDezenaSegundos = 7'b0100100;
                4'b0110 : OutDezenaSegundos = 7'b0100000;
                4'b0111 : OutDezenaSegundos = 7'b0001101;
                4'b1000 : OutDezenaSegundos = 7'b0000000;
                4'b1001 : OutDezenaSegundos = 7'b0000100;
                endcase
  
        always@(UnidadeSegundos)
                case(UnidadeSegundos)
                4'b0000 : OutUnidadeSegundos = 7'b0000001;
                4'b0001 : OutUnidadeSegundos = 7'b1001111;
                4'b0010 : OutUnidadeSegundos = 7'b0010010;
                4'b0011 : OutUnidadeSegundos = 7'b0000110;
                4'b0100 : OutUnidadeSegundos = 7'b1001100;
                4'b0101 : OutUnidadeSegundos = 7'b0100100;
                4'b0110 : OutUnidadeSegundos = 7'b0100000;
                4'b0111 : OutUnidadeSegundos = 7'b0001101;
                4'b1000 : OutUnidadeSegundos = 7'b0000000;
                4'b1001 : OutUnidadeSegundos = 7'b0000100;
                endcase

endmodule

nivel2/decoder/decoder_tb.v
`timescale 1ns/1ns
`include "decoder.v"

module decoder_tb;

    reg [3:0] Minutos_TB, DezenaSegundos_TB, UnidadeSegundos_TB;
  	wire [6:0] OutMinutos_TB, OutDezenaSegundos_TB, OutUnidadeSegundos_TB;

  	decoder DUT(.Minutos(Minutos_TB), .DezenaSegundos(DezenaSegundos_TB), .UnidadeSegundos(UnidadeSegundos_TB), .OutMinutos(OutMinutos_TB), .OutDezenaSegundos(OutDezenaSegundos_TB), .OutUnidadeSegundos(OutUnidadeSegundos_TB));

    initial
        begin

            $dumpfile("decoder_tb.vcd");
            $dumpvars(0, decoder_tb);

                Minutos_TB=4'b0000; DezenaSegundos_TB=4'b0000; UnidadeSegundos_TB=4'b0000;  
            #5  Minutos_TB=4'b0001; DezenaSegundos_TB=4'b0001; UnidadeSegundos_TB=4'b0001; 
         	  #5  Minutos_TB=4'b0010; DezenaSegundos_TB=4'b0010; UnidadeSegundos_TB=4'b0010;
            #5  Minutos_TB=4'b0011; DezenaSegundos_TB=4'b0011; UnidadeSegundos_TB=4'b0011;
            #5  Minutos_TB=4'b0100; DezenaSegundos_TB=4'b0100; UnidadeSegundos_TB=4'b0100;
            #5  Minutos_TB=4'b0101; DezenaSegundos_TB=4'b0101; UnidadeSegundos_TB=4'b0101;
          	#5  Minutos_TB=4'b0110; DezenaSegundos_TB=4'b0110; UnidadeSegundos_TB=4'b0110;
            #5  Minutos_TB=4'b0111; DezenaSegundos_TB=4'b0111; UnidadeSegundos_TB=4'b0111;
          	#5  Minutos_TB=4'b1000; DezenaSegundos_TB=4'b1000; UnidadeSegundos_TB=4'b1000;
            #5  Minutos_TB=4'b1001; DezenaSegundos_TB=4'b1001; UnidadeSegundos_TB=4'b1001;    
        end
endmodule

nivel2/decoder/decoder_tb.vcd
$date
	Sat Apr 22 23:16:20 2023
$end
$version
	Icarus Verilog
$end
$timescale
	1ns
$end
$scope module decoder_tb $end
$var wire 7 ! OutUnidadeSegundos_TB [6:0] $end
$var wire 7 " OutMinutos_TB [6:0] $end
$var wire 7 # OutDezenaSegundos_TB [6:0] $end
$var reg 4 $ DezenaSegundos_TB [3:0] $end
$var reg 4 % Minutos_TB [3:0] $end
$var reg 4 & UnidadeSegundos_TB [3:0] $end
$scope module DUT $end
$var wire 4 ' DezenaSegundos [3:0] $end
$var wire 4 ( Minutos [3:0] $end
$var wire 4 ) UnidadeSegundos [3:0] $end
$var reg 7 * OutDezenaSegundos [6:0] $end
$var reg 7 + OutMinutos [6:0] $end
$var reg 7 , OutUnidadeSegundos [6:0] $end
$upscope $end
$upscope $end
$enddefinitions $end
$comment Show the parameter values. $end
$dumpall
$end
#0
$dumpvars
b1 ,
b1 +
b1 *
b0 )
b0 (
b0 '
b0 &
b0 %
b0 $
b1 #
b1 "
b1 !
$end
#5
b1001111 !
b1001111 ,
b1001111 #
b1001111 *
b1001111 "
b1001111 +
b1 &
b1 )
b1 $
b1 '
b1 %
b1 (
#10
b10010 !
b10010 ,
b10010 #
b10010 *
b10010 "
b10010 +
b10 &
b10 )
b10 $
b10 '
b10 %
b10 (
#15
b110 !
b110 ,
b110 #
b110 *
b110 "
b110 +
b11 &
b11 )
b11 $
b11 '
b11 %
b11 (
#20
b1001100 !
b1001100 ,
b1001100 #
b1001100 *
b1001100 "
b1001100 +
b100 &
b100 )
b100 $
b100 '
b100 %
b100 (
#25
b100100 !
b100100 ,
b100100 #
b100100 *
b100100 "
b100100 +
b101 &
b101 )
b101 $
b101 '
b101 %
b101 (
#30
b100000 !
b100000 ,
b100000 #
b100000 *
b100000 "
b100000 +
b110 &
b110 )
b110 $
b110 '
b110 %
b110 (
#35
b1101 !
b1101 ,
b1101 #
b1101 *
b1101 "
b1101 +
b111 &
b111 )
b111 $
b111 '
b111 %
b111 (
#40
b0 !
b0 ,
b0 #
b0 *
b0 "
b0 +
b1000 &
b1000 )
b1000 $
b1000 '
b1000 %
b1000 (
#45
b100 !
b100 ,
b100 #
b100 *
b100 "
b100 +
b1001 &
b1001 )
b1001 $
b1001 '
b1001 %
b1001 (
