nivel2/decoder/decoder.v
module decoder (output wire [6:0] OutMinutos, OutDezenaSeg, OutUnidadeSeg,
                input wire [3:0] Minutos, DezenaSeg, UnidadeSeg);


        assign OutMinutos = (Minutos == 4'b0000) ? 7'b111_1110 : 
                            (Minutos == 4'b0001) ? 7'b011_0000 : 
                            (Minutos == 4'b0010) ? 7'b110_1101 : 
                            (Minutos == 4'b0011) ? 7'b111_1001 : 
                            (Minutos == 4'b0100) ? 7'b011_0011 : 
                            (Minutos == 4'b0101) ? 7'b101_1011 : 
                            (Minutos == 4'b0110) ? 7'b101_1111 : 
                            (Minutos == 4'b0111) ? 7'b111_0000 : 
                            (Minutos == 4'b1000) ? 7'b111_1111 : 
                            (Minutos == 4'b1001) ? 7'b111_0011 : 8'bXXXX_XXXX;


        assign OutDezenaSeg =   (DezenaSeg == 4'b0000) ? 7'b111_1110 : 
                                (DezenaSeg == 4'b0001) ? 7'b011_0000 : 
                                (DezenaSeg == 4'b0010) ? 7'b110_1101 : 
                                (DezenaSeg == 4'b0011) ? 7'b111_1001 : 
                                (DezenaSeg == 4'b0100) ? 7'b011_0011 : 
                                (DezenaSeg == 4'b0101) ? 7'b101_1011 : 
                                (DezenaSeg == 4'b0110) ? 7'b101_1111 : 
                                (DezenaSeg == 4'b0111) ? 7'b111_0000 : 
                                (DezenaSeg == 4'b1000) ? 7'b111_1111 : 
                                (DezenaSeg == 4'b1001) ? 7'b111_0011 : 8'bXXXX_XXXX;

        assign OutUnidadeSeg =  (UnidadeSeg == 4'b0000) ? 7'b111_1110 : 
                                (UnidadeSeg == 4'b0001) ? 7'b011_0000 : 
                                (UnidadeSeg == 4'b0010) ? 7'b110_1101 : 
                                (UnidadeSeg == 4'b0011) ? 7'b111_1001 : 
                                (UnidadeSeg == 4'b0100) ? 7'b011_0011 : 
                                (UnidadeSeg == 4'b0101) ? 7'b101_1011 : 
                                (UnidadeSeg == 4'b0110) ? 7'b101_1111 : 
                                (UnidadeSeg == 4'b0111) ? 7'b111_0000 : 
                                (UnidadeSeg == 4'b1000) ? 7'b111_1111 : 
                                (UnidadeSeg == 4'b1001) ? 7'b111_0011 : 8'bXXXX_XXXX;
endmodule

nivel2/decoder/decoder_tb.v
`include "decoder.v"
`timescale 1ns/1ns
module decoder_tb;

  reg [3:0] Minutos;
  reg [3:0] DezenaSeg;
  reg [3:0] UnidadeSeg;

  wire [6:0] OutMinutos;
  wire [6:0] OutDezenaSeg;
  wire [6:0] OutUnidadeSeg;


  decoder dut (
    .OutMinutos(OutMinutos),
    .OutDezenaSeg(OutDezenaSeg),
    .OutUnidadeSeg(OutUnidadeSeg),
    .Minutos(Minutos),
    .DezenaSeg(DezenaSeg),
    .UnidadeSeg(UnidadeSeg) );

    initial begin
        $dumpfile("decoder_tb.vcd");
        $dumpvars(0, decoder_tb);

        Minutos = 4'b0000; 
        DezenaSeg = 4'b0000; 
        UnidadeSeg = 4'b0000;

        #5 Minutos = 4'b0001; 
        DezenaSeg = 4'b0001; 
        UnidadeSeg = 4'b0001;

        #5 Minutos = 4'b0010; 
        DezenaSeg = 4'b0010; 
        UnidadeSeg = 4'b0010;

        #5 Minutos = 4'b0011; 
        DezenaSeg = 4'b0011; 
        UnidadeSeg = 4'b0011;

        #5 Minutos = 4'b0100; 
        DezenaSeg = 4'b0100; 
        UnidadeSeg = 4'b0100;

        #5 Minutos = 4'b0101; 
        DezenaSeg = 4'b0101; 
        UnidadeSeg = 4'b0101;

        #5 Minutos = 4'b0110; 
        DezenaSeg = 4'b0110; 
        UnidadeSeg = 4'b0110;

        #5 Minutos = 4'b0111; 
        DezenaSeg = 4'b0111; 
        UnidadeSeg = 4'b0111;

        #5 Minutos = 4'b1000; 
        DezenaSeg = 4'b1000; 
        UnidadeSeg = 4'b1000;

        #5 Minutos = 4'b1001; 
        DezenaSeg = 4'b1001; 
        UnidadeSeg = 4'b1001;
    end

endmodule

nivel2/decoder/decoder_tb.vcd
$date
	Sat Apr 22 12:09:13 2023
$end
$version
	Icarus Verilog
$end
$timescale
	1ns
$end
$scope module decoder_tb $end
$var wire 7 ! OutUnidadeSeg [6:0] $end
$var wire 7 " OutMinutos [6:0] $end
$var wire 7 # OutDezenaSeg [6:0] $end
$var reg 4 $ DezenaSeg [3:0] $end
$var reg 4 % Minutos [3:0] $end
$var reg 4 & UnidadeSeg [3:0] $end
$scope module dut $end
$var wire 4 ' DezenaSeg [3:0] $end
$var wire 4 ( Minutos [3:0] $end
$var wire 4 ) UnidadeSeg [3:0] $end
$var wire 7 * OutUnidadeSeg [6:0] $end
$var wire 7 + OutMinutos [6:0] $end
$var wire 7 , OutDezenaSeg [6:0] $end
$upscope $end
$upscope $end
$enddefinitions $end
$comment Show the parameter values. $end
$dumpall
$end
#0
$dumpvars
b1111110 ,
b1111110 +
b1111110 *
b0 )
b0 (
b0 '
b0 &
b0 %
b0 $
b1111110 #
b1111110 "
b1111110 !
$end
#5
b110000 !
b110000 *
b110000 #
b110000 ,
b110000 "
b110000 +
b1 &
b1 )
b1 $
b1 '
b1 %
b1 (
#10
b1101101 !
b1101101 *
b1101101 #
b1101101 ,
b1101101 "
b1101101 +
b10 &
b10 )
b10 $
b10 '
b10 %
b10 (
#15
b1111001 !
b1111001 *
b1111001 #
b1111001 ,
b1111001 "
b1111001 +
b11 &
b11 )
b11 $
b11 '
b11 %
b11 (
#20
b110011 !
b110011 *
b110011 #
b110011 ,
b110011 "
b110011 +
b100 &
b100 )
b100 $
b100 '
b100 %
b100 (
#25
b1011011 !
b1011011 *
b1011011 #
b1011011 ,
b1011011 "
b1011011 +
b101 &
b101 )
b101 $
b101 '
b101 %
b101 (
#30
b1011111 !
b1011111 *
b1011111 #
b1011111 ,
b1011111 "
b1011111 +
b110 &
b110 )
b110 $
b110 '
b110 %
b110 (
#35
b1110000 !
b1110000 *
b1110000 #
b1110000 ,
b1110000 "
b1110000 +
b111 &
b111 )
b111 $
b111 '
b111 %
b111 (
#40
b1111111 !
b1111111 *
b1111111 #
b1111111 ,
b1111111 "
b1111111 +
b1000 &
b1000 )
b1000 $
b1000 '
b1000 %
b1000 (
#45
b1110011 !
b1110011 *
b1110011 #
b1110011 ,
b1110011 "
b1110011 +
b1001 &
b1001 )
b1001 $
b1001 '
b1001 %
b1001 (
