nivel1/nivel2/entrada_timer_controle/mux/mux.v
module mux(
    input wire enablen,
    input wire signal,
    input clk,
    output reg pgt_1Hz
);

    always @(*) begin
        if (enablen == 1'b0) begin
            pgt_1Hz = signal;
        end

        else
            pgt_1Hz = clk;
    end
    
endmodule

nivel1/nivel2/entrada_timer_controle/encoder/encoder.v
module encoder(
    input wire [9:0] keyboard,
    input wire enablen,
    output reg [3:0] bcd,
    output reg valid_data
);

    always @(keyboard)
        if (enablen == 1'b0) begin
            case(keyboard)
                10'b1000000000: bcd = 4'b1001;
                10'b0100000000: bcd = 4'b1000;
                10'b0010000000: bcd = 4'b0111;
                10'b0001000000: bcd = 4'b0110;
                10'b0000100000: bcd = 4'b0101;
                10'b0000010000: bcd = 4'b0100;
                10'b0000001000: bcd = 4'b0011;
                10'b0000000100: bcd = 4'b0010;
                10'b0000000010: bcd = 4'b0001;
                10'b0000000001: bcd = 4'b0000;
            endcase
            valid_data = 1'b1;
        end

        else begin
            valid_data = 1'b0;
        end

endmodule

nivel1/nivel2/entrada_timer_controle/counter_non_recycling/counter_non_recycling.v
module counter_non_recycling(
    input clk,
    input clear,
    output reg signal
);

    reg [2:0] counter;

    always @(posedge clk or posedge clear) begin
        if (clear) begin
            counter = 3'b000;
            signal = 1'b0;
        end

        else
            if (counter == 3'b011) begin
                signal = 1'b1;
                counter = counter + 1'b1;
            end

            else if (counter < 3'b111) begin
                counter = counter + 1'b1;
            end
        
    end
    
endmodule

nivel1/nivel2/entrada_timer_controle/counter_freq/counter_freq.v
module counter_freq(
    input clk,
    output reg clk_out
);

    reg [5:0] count = 6'b000000;
    initial clk_out = 1'b0;

    always @(posedge clk) begin
        count = count + 1'b1;
        if (count >= 50) begin
            count = 6'b000000;
            clk_out = !clk_out;
        end
    end

endmodule

nivel1/nivel2/entrada_timer_controle/control_timer.v
`include "nivel2/entrada_timer_controle/counter_freq/counter_freq.v"
`include "nivel2/entrada_timer_controle/counter_non_recycling/counter_non_recycling.v"
`include "nivel2/entrada_timer_controle/encoder/encoder.v"
`include "nivel2/entrada_timer_controle/mux/mux.v"

module control_timer(
    input wire [9:0] keyboard,
    input wire enablen,
    input clk,
    output wire [3:0] d,
    output reg loadn,
    output reg pgt_1Hz
);

    reg clk_1Hz;
    reg signal;

    counter_freq counter_freq(
        .clk(clk),
        .clk_out(clk_1Hz)
    );

    counter_non_recycling counter_non_recycling(
        .clk(clk), .clear(loadn),
        .signal(signal)
    );

    encoder encoder(
        .keyboard(keyboard), .enablen(enablen),
        .bcd(d), .valid_data(loadn)
    );

    mux mux(
        .enablen(enablen), .signal(signal), .clk(clk_1Hz),
        .pgt_1Hz(pgt_1Hz)
    );

endmodule

nivel1/nivel2/entrada_timer_controle/control_timer_tb.v
`timescale 1ns/1ns
`include "control_timer.v"

module control_timer_tb;

    reg [9:0] keyboard_tb;
    reg enablen_tb;
    reg clk_tb;
    wire [3:0] d_tb;
    wire loadn_tb;
    wire pgt_1Hz_tb;

    control_timer dut(
        .keyboard(keyboard_tb), .enablen(enablen_tb), .clk(clk_tb),
        .d(d_tb), .loadn(loadn_tb), .pgt_1Hz(pgt_1Hz_tb)
    );

    initial begin
        $dumpfile("control_timer_tb.vcd");
        $dumpvars(0, control_timer_tb);

            #1 keyboard_tb = 10'b1000000000;
            clk_tb = 1;
            enablen_tb = 0;
            repeat(201)
                #1 clk_tb = ~clk_tb;
            
            #1 keyboard_tb = 10'b0100000000;
            clk_tb = 1;
            repeat(201)
                #1 clk_tb = ~clk_tb;

            #1 keyboard_tb = 10'b100000000;
            clk_tb = 1;
            enablen_tb = 1;
            repeat(201)
                #1 clk_tb = ~clk_tb;

            enablen_tb = 0;
            repeat(201)
                #1 clk_tb = ~clk_tb;
            
    end

endmodule

nivel1/nivel2/entrada_timer_controle/control_timer_tb.vcd
$date
	Sat Apr 22 23:19:11 2023
$end
$version
	Icarus Verilog
$end
$timescale
	1ns
$end
$scope module control_timer_tb $end
$var wire 1 ! pgt_1Hz_tb $end
$var wire 1 " loadn_tb $end
$var wire 4 # d_tb [3:0] $end
$var reg 1 $ clk_tb $end
$var reg 1 % enablen_tb $end
$var reg 10 & keyboard_tb [9:0] $end
$scope module dut $end
$var wire 1 $ clk $end
$var wire 1 % enablen $end
$var wire 10 ' keyboard [9:0] $end
$var wire 1 ( signal $end
$var wire 1 ! pgt_1Hz $end
$var wire 1 " loadn $end
$var wire 4 ) d [3:0] $end
$var wire 1 * clk_1Hz $end
$scope module counter_freq $end
$var wire 1 $ clk $end
$var reg 1 * clk_out $end
$var reg 6 + count [5:0] $end
$upscope $end
$scope module counter_non_recycling $end
$var wire 1 $ clk $end
$var wire 1 " clear $end
$var reg 3 , counter [2:0] $end
$var reg 1 ( signal $end
$upscope $end
$scope module encoder $end
$var wire 1 % enablen $end
$var wire 10 - keyboard [9:0] $end
$var reg 4 . bcd [3:0] $end
$var reg 1 " valid_data $end
$upscope $end
$scope module mux $end
$var wire 1 * clk $end
$var wire 1 % enablen $end
$var wire 1 ( signal $end
$var reg 1 ! pgt_1Hz $end
$upscope $end
$upscope $end
$upscope $end
$enddefinitions $end
#0
$dumpvars
bx .
bx -
bx ,
b0 +
0*
bx )
x(
bx '
bx &
x%
x$
bx #
x"
0!
$end
#1
x!
b1 +
b0 ,
1"
b1001 #
b1001 )
b1001 .
0%
1$
b1000000000 &
b1000000000 '
b1000000000 -
#2
0$
#3
b10 +
1$
#4
0$
#5
b11 +
1$
#6
0$
#7
b100 +
1$
#8
0$
#9
b101 +
1$
#10
0$
#11
b110 +
1$
#12
0$
#13
b111 +
1$
#14
0$
#15
b1000 +
1$
#16
0$
#17
b1001 +
1$
#18
0$
#19
b1010 +
1$
#20
0$
#21
b1011 +
1$
#22
0$
#23
b1100 +
1$
#24
0$
#25
b1101 +
1$
#26
0$
#27
b1110 +
1$
#28
0$
#29
b1111 +
1$
#30
0$
#31
b10000 +
1$
#32
0$
#33
b10001 +
1$
#34
0$
#35
b10010 +
1$
#36
0$
#37
b10011 +
1$
#38
0$
#39
b10100 +
1$
#40
0$
#41
b10101 +
1$
#42
0$
#43
b10110 +
1$
#44
0$
#45
b10111 +
1$
#46
0$
#47
b11000 +
1$
#48
0$
#49
b11001 +
1$
#50
0$
#51
b11010 +
1$
#52
0$
#53
b11011 +
1$
#54
0$
#55
b11100 +
1$
#56
0$
#57
b11101 +
1$
#58
0$
#59
b11110 +
1$
#60
0$
#61
b11111 +
1$
#62
0$
#63
b100000 +
1$
#64
0$
#65
b100001 +
1$
#66
0$
#67
b100010 +
1$
#68
0$
#69
b100011 +
1$
#70
0$
#71
b100100 +
1$
#72
0$
#73
b100101 +
1$
#74
0$
#75
b100110 +
1$
#76
0$
#77
b100111 +
1$
#78
0$
#79
b101000 +
1$
#80
0$
#81
b101001 +
1$
#82
0$
#83
b101010 +
1$
#84
0$
#85
b101011 +
1$
#86
0$
#87
b101100 +
1$
#88
0$
#89
b101101 +
1$
#90
0$
#91
b101110 +
1$
#92
0$
#93
b101111 +
1$
#94
0$
#95
b110000 +
1$
#96
0$
#97
b110001 +
1$
#98
0$
#99
1*
b0 +
1$
#100
0$
#101
b1 +
1$
#102
0$
#103
b10 +
1$
#104
0$
#105
b11 +
1$
#106
0$
#107
b100 +
1$
#108
0$
#109
b101 +
1$
#110
0$
#111
b110 +
1$
#112
0$
#113
b111 +
1$
#114
0$
#115
b1000 +
1$
#116
0$
#117
b1001 +
1$
#118
0$
#119
b1010 +
1$
#120
0$
#121
b1011 +
1$
#122
0$
#123
b1100 +
1$
#124
0$
#125
b1101 +
1$
#126
0$
#127
b1110 +
1$
#128
0$
#129
b1111 +
1$
#130
0$
#131
b10000 +
1$
#132
0$
#133
b10001 +
1$
#134
0$
#135
b10010 +
1$
#136
0$
#137
b10011 +
1$
#138
0$
#139
b10100 +
1$
#140
0$
#141
b10101 +
1$
#142
0$
#143
b10110 +
1$
#144
0$
#145
b10111 +
1$
#146
0$
#147
b11000 +
1$
#148
0$
#149
b11001 +
1$
#150
0$
#151
b11010 +
1$
#152
0$
#153
b11011 +
1$
#154
0$
#155
b11100 +
1$
#156
0$
#157
b11101 +
1$
#158
0$
#159
b11110 +
1$
#160
0$
#161
b11111 +
1$
#162
0$
#163
b100000 +
1$
#164
0$
#165
b100001 +
1$
#166
0$
#167
b100010 +
1$
#168
0$
#169
b100011 +
1$
#170
0$
#171
b100100 +
1$
#172
0$
#173
b100101 +
1$
#174
0$
#175
b100110 +
1$
#176
0$
#177
b100111 +
1$
#178
0$
#179
b101000 +
1$
#180
0$
#181
b101001 +
1$
#182
0$
#183
b101010 +
1$
#184
0$
#185
b101011 +
1$
#186
0$
#187
b101100 +
1$
#188
0$
#189
b101101 +
1$
#190
0$
#191
b101110 +
1$
#192
0$
#193
b101111 +
1$
#194
0$
#195
b110000 +
1$
#196
0$
#197
b110001 +
1$
#198
0$
#199
0*
b0 +
1$
#200
0$
#201
b1 +
1$
#202
0$
#203
b10 +
b1000 #
b1000 )
b1000 .
1$
b100000000 &
b100000000 '
b100000000 -
#204
0$
#205
b11 +
1$
#206
0$
#207
b100 +
1$
#208
0$
#209
b101 +
1$
#210
0$
#211
b110 +
1$
#212
0$
#213
b111 +
1$
#214
0$
#215
b1000 +
1$
#216
0$
#217
b1001 +
1$
#218
0$
#219
b1010 +
1$
#220
0$
#221
b1011 +
1$
#222
0$
#223
b1100 +
1$
#224
0$
#225
b1101 +
1$
#226
0$
#227
b1110 +
1$
#228
0$
#229
b1111 +
1$
#230
0$
#231
b10000 +
1$
#232
0$
#233
b10001 +
1$
#234
0$
#235
b10010 +
1$
#236
0$
#237
b10011 +
1$
#238
0$
#239
b10100 +
1$
#240
0$
#241
b10101 +
1$
#242
0$
#243
b10110 +
1$
#244
0$
#245
b10111 +
1$
#246
0$
#247
b11000 +
1$
#248
0$
#249
b11001 +
1$
#250
0$
#251
b11010 +
1$
#252
0$
#253
b11011 +
1$
#254
0$
#255
b11100 +
1$
#256
0$
#257
b11101 +
1$
#258
0$
#259
b11110 +
1$
#260
0$
#261
b11111 +
1$
#262
0$
#263
b100000 +
1$
#264
0$
#265
b100001 +
1$
#266
0$
#267
b100010 +
1$
#268
0$
#269
b100011 +
1$
#270
0$
#271
b100100 +
1$
#272
0$
#273
b100101 +
1$
#274
0$
#275
b100110 +
1$
#276
0$
#277
b100111 +
1$
#278
0$
#279
b101000 +
1$
#280
0$
#281
b101001 +
1$
#282
0$
#283
b101010 +
1$
#284
0$
#285
b101011 +
1$
#286
0$
#287
b101100 +
1$
#288
0$
#289
b101101 +
1$
#290
0$
#291
b101110 +
1$
#292
0$
#293
b101111 +
1$
#294
0$
#295
b110000 +
1$
#296
0$
#297
b110001 +
1$
#298
0$
#299
1*
b0 +
1$
#300
0$
#301
b1 +
1$
#302
0$
#303
b10 +
1$
#304
0$
#305
b11 +
1$
#306
0$
#307
b100 +
1$
#308
0$
#309
b101 +
1$
#310
0$
#311
b110 +
1$
#312
0$
#313
b111 +
1$
#314
0$
#315
b1000 +
1$
#316
0$
#317
b1001 +
1$
#318
0$
#319
b1010 +
1$
#320
0$
#321
b1011 +
1$
#322
0$
#323
b1100 +
1$
#324
0$
#325
b1101 +
1$
#326
0$
#327
b1110 +
1$
#328
0$
#329
b1111 +
1$
#330
0$
#331
b10000 +
1$
#332
0$
#333
b10001 +
1$
#334
0$
#335
b10010 +
1$
#336
0$
#337
b10011 +
1$
#338
0$
#339
b10100 +
1$
#340
0$
#341
b10101 +
1$
#342
0$
#343
b10110 +
1$
#344
0$
#345
b10111 +
1$
#346
0$
#347
b11000 +
1$
#348
0$
#349
b11001 +
1$
#350
0$
#351
b11010 +
1$
#352
0$
#353
b11011 +
1$
#354
0$
#355
b11100 +
1$
#356
0$
#357
b11101 +
1$
#358
0$
#359
b11110 +
1$
#360
0$
#361
b11111 +
1$
#362
0$
#363
b100000 +
1$
#364
0$
#365
b100001 +
1$
#366
0$
#367
b100010 +
1$
#368
0$
#369
b100011 +
1$
#370
0$
#371
b100100 +
1$
#372
0$
#373
b100101 +
1$
#374
0$
#375
b100110 +
1$
#376
0$
#377
b100111 +
1$
#378
0$
#379
b101000 +
1$
#380
0$
#381
b101001 +
1$
#382
0$
#383
b101010 +
1$
#384
0$
#385
b101011 +
1$
#386
0$
#387
b101100 +
1$
#388
0$
#389
b101101 +
1$
#390
0$
#391
b101110 +
1$
#392
0$
#393
b101111 +
1$
#394
0$
#395
b110000 +
1$
#396
0$
#397
b110001 +
1$
#398
0$
#399
0*
b0 +
1$
#400
0$
#401
b1 +
1$
#402
0$
#403
b10 +
1$
#404
0$
#405
0!
b11 +
1%
1$
#406
0$
#407
b100 +
1$
#408
0$
#409
b101 +
1$
#410
0$
#411
b110 +
1$
#412
0$
#413
b111 +
1$
#414
0$
#415
b1000 +
1$
#416
0$
#417
b1001 +
1$
#418
0$
#419
b1010 +
1$
#420
0$
#421
b1011 +
1$
#422
0$
#423
b1100 +
1$
#424
0$
#425
b1101 +
1$
#426
0$
#427
b1110 +
1$
#428
0$
#429
b1111 +
1$
#430
0$
#431
b10000 +
1$
#432
0$
#433
b10001 +
1$
#434
0$
#435
b10010 +
1$
#436
0$
#437
b10011 +
1$
#438
0$
#439
b10100 +
1$
#440
0$
#441
b10101 +
1$
#442
0$
#443
b10110 +
1$
#444
0$
#445
b10111 +
1$
#446
0$
#447
b11000 +
1$
#448
0$
#449
b11001 +
1$
#450
0$
#451
b11010 +
1$
#452
0$
#453
b11011 +
1$
#454
0$
#455
b11100 +
1$
#456
0$
#457
b11101 +
1$
#458
0$
#459
b11110 +
1$
#460
0$
#461
b11111 +
1$
#462
0$
#463
b100000 +
1$
#464
0$
#465
b100001 +
1$
#466
0$
#467
b100010 +
1$
#468
0$
#469
b100011 +
1$
#470
0$
#471
b100100 +
1$
#472
0$
#473
b100101 +
1$
#474
0$
#475
b100110 +
1$
#476
0$
#477
b100111 +
1$
#478
0$
#479
b101000 +
1$
#480
0$
#481
b101001 +
1$
#482
0$
#483
b101010 +
1$
#484
0$
#485
b101011 +
1$
#486
0$
#487
b101100 +
1$
#488
0$
#489
b101101 +
1$
#490
0$
#491
b101110 +
1$
#492
0$
#493
b101111 +
1$
#494
0$
#495
b110000 +
1$
#496
0$
#497
b110001 +
1$
#498
0$
#499
1!
1*
b0 +
1$
#500
0$
#501
b1 +
1$
#502
0$
#503
b10 +
1$
#504
0$
#505
b11 +
1$
#506
0$
#507
b100 +
1$
#508
0$
#509
b101 +
1$
#510
0$
#511
b110 +
1$
#512
0$
#513
b111 +
1$
#514
0$
#515
b1000 +
1$
#516
0$
#517
b1001 +
1$
#518
0$
#519
b1010 +
1$
#520
0$
#521
b1011 +
1$
#522
0$
#523
b1100 +
1$
#524
0$
#525
b1101 +
1$
#526
0$
#527
b1110 +
1$
#528
0$
#529
b1111 +
1$
#530
0$
#531
b10000 +
1$
#532
0$
#533
b10001 +
1$
#534
0$
#535
b10010 +
1$
#536
0$
#537
b10011 +
1$
#538
0$
#539
b10100 +
1$
#540
0$
#541
b10101 +
1$
#542
0$
#543
b10110 +
1$
#544
0$
#545
b10111 +
1$
#546
0$
#547
b11000 +
1$
#548
0$
#549
b11001 +
1$
#550
0$
#551
b11010 +
1$
#552
0$
#553
b11011 +
1$
#554
0$
#555
b11100 +
1$
#556
0$
#557
b11101 +
1$
#558
0$
#559
b11110 +
1$
#560
0$
#561
b11111 +
1$
#562
0$
#563
b100000 +
1$
#564
0$
#565
b100001 +
1$
#566
0$
#567
b100010 +
1$
#568
0$
#569
b100011 +
1$
#570
0$
#571
b100100 +
1$
#572
0$
#573
b100101 +
1$
#574
0$
#575
b100110 +
1$
#576
0$
#577
b100111 +
1$
#578
0$
#579
b101000 +
1$
#580
0$
#581
b101001 +
1$
#582
0$
#583
b101010 +
1$
#584
0$
#585
b101011 +
1$
#586
0$
#587
b101100 +
1$
#588
0$
#589
b101101 +
1$
#590
0$
#591
b101110 +
1$
#592
0$
#593
b101111 +
1$
#594
0$
#595
b110000 +
1$
#596
0$
#597
b110001 +
1$
#598
0$
#599
0!
0*
b0 +
1$
#600
0$
#601
b1 +
1$
#602
0$
#603
b10 +
1$
#604
0$
#605
b11 +
1$
#606
x!
0%
0$
#607
b100 +
1$
#608
0$
#609
b101 +
1$
#610
0$
#611
b110 +
1$
#612
0$
#613
b111 +
1$
#614
0$
#615
b1000 +
1$
#616
0$
#617
b1001 +
1$
#618
0$
#619
b1010 +
1$
#620
0$
#621
b1011 +
1$
#622
0$
#623
b1100 +
1$
#624
0$
#625
b1101 +
1$
#626
0$
#627
b1110 +
1$
#628
0$
#629
b1111 +
1$
#630
0$
#631
b10000 +
1$
#632
0$
#633
b10001 +
1$
#634
0$
#635
b10010 +
1$
#636
0$
#637
b10011 +
1$
#638
0$
#639
b10100 +
1$
#640
0$
#641
b10101 +
1$
#642
0$
#643
b10110 +
1$
#644
0$
#645
b10111 +
1$
#646
0$
#647
b11000 +
1$
#648
0$
#649
b11001 +
1$
#650
0$
#651
b11010 +
1$
#652
0$
#653
b11011 +
1$
#654
0$
#655
b11100 +
1$
#656
0$
#657
b11101 +
1$
#658
0$
#659
b11110 +
1$
#660
0$
#661
b11111 +
1$
#662
0$
#663
b100000 +
1$
#664
0$
#665
b100001 +
1$
#666
0$
#667
b100010 +
1$
#668
0$
#669
b100011 +
1$
#670
0$
#671
b100100 +
1$
#672
0$
#673
b100101 +
1$
#674
0$
#675
b100110 +
1$
#676
0$
#677
b100111 +
1$
#678
0$
#679
b101000 +
1$
#680
0$
#681
b101001 +
1$
#682
0$
#683
b101010 +
1$
#684
0$
#685
b101011 +
1$
#686
0$
#687
b101100 +
1$
#688
0$
#689
b101101 +
1$
#690
0$
#691
b101110 +
1$
#692
0$
#693
b101111 +
1$
#694
0$
#695
b110000 +
1$
#696
0$
#697
b110001 +
1$
#698
0$
#699
1*
b0 +
1$
#700
0$
#701
b1 +
1$
#702
0$
#703
b10 +
1$
#704
0$
#705
b11 +
1$
#706
0$
#707
b100 +
1$
#708
0$
#709
b101 +
1$
#710
0$
#711
b110 +
1$
#712
0$
#713
b111 +
1$
#714
0$
#715
b1000 +
1$
#716
0$
#717
b1001 +
1$
#718
0$
#719
b1010 +
1$
#720
0$
#721
b1011 +
1$
#722
0$
#723
b1100 +
1$
#724
0$
#725
b1101 +
1$
#726
0$
#727
b1110 +
1$
#728
0$
#729
b1111 +
1$
#730
0$
#731
b10000 +
1$
#732
0$
#733
b10001 +
1$
#734
0$
#735
b10010 +
1$
#736
0$
#737
b10011 +
1$
#738
0$
#739
b10100 +
1$
#740
0$
#741
b10101 +
1$
#742
0$
#743
b10110 +
1$
#744
0$
#745
b10111 +
1$
#746
0$
#747
b11000 +
1$
#748
0$
#749
b11001 +
1$
#750
0$
#751
b11010 +
1$
#752
0$
#753
b11011 +
1$
#754
0$
#755
b11100 +
1$
#756
0$
#757
b11101 +
1$
#758
0$
#759
b11110 +
1$
#760
0$
#761
b11111 +
1$
#762
0$
#763
b100000 +
1$
#764
0$
#765
b100001 +
1$
#766
0$
#767
b100010 +
1$
#768
0$
#769
b100011 +
1$
#770
0$
#771
b100100 +
1$
#772
0$
#773
b100101 +
1$
#774
0$
#775
b100110 +
1$
#776
0$
#777
b100111 +
1$
#778
0$
#779
b101000 +
1$
#780
0$
#781
b101001 +
1$
#782
0$
#783
b101010 +
1$
#784
0$
#785
b101011 +
1$
#786
0$
#787
b101100 +
1$
#788
0$
#789
b101101 +
1$
#790
0$
#791
b101110 +
1$
#792
0$
#793
b101111 +
1$
#794
0$
#795
b110000 +
1$
#796
0$
#797
b110001 +
1$
#798
0$
#799
0*
b0 +
1$
#800
0$
#801
b1 +
1$
#802
0$
#803
b10 +
1$
#804
0$
#805
b11 +
1$
#806
0$
#807
b100 +
1$
