nivel1/nivel2/magnetron/comb_logic/comb_logic.v
module comb_logic(input wire startn, stopn, 
                  clearn, door_closed, timer_done,
                  output reg set, reset);

    always @(startn or stopn or clearn or
             door_closed or timer_done) 

        begin
            if ((!startn) && (stopn) && (clearn) && (door_closed) && (!timer_done))
                set = 1;
            else
                set = 0;
            
            if ((startn) || (!stopn) || (!clearn) || (!door_closed) || (timer_done))
                reset = 1;
            else
                reset = 0;
        end
endmodule

nivel1/nivel2/magnetron/comb_logic/comb_logic_tb.v
`timescale 1ns/1ps
`include "comb_logic.v"

module comb_logic_tb();

    reg startn_TB, stopn_TB, clearn_TB, door_closed_TB , timer_done_TB;

    comb_logic DUT(.startn(startn_TB),.stopn(stopn_TB),.clearn(clearn_TB),.door_closed(door_closed_TB),.timer_done(timer_done_TB));

    initial 
        begin
            
            $dumpfile("comb_logic_tb.vcd");
            $dumpvars(0,comb_logic_tb);

                startn_TB=1; stopn_TB=1; clearn_TB=1; door_closed_TB=1; timer_done_TB=1;
            #3 startn_TB=0; stopn_TB=1; clearn_TB=1; door_closed_TB=1; timer_done_TB=0;
            #3 startn_TB=0; stopn_TB=1; clearn_TB=0; door_closed_TB=1; timer_done_TB=1;
            #3 startn_TB=0; stopn_TB=1; clearn_TB=1; door_closed_TB=1; timer_done_TB=0;
            #3 startn_TB=0; stopn_TB=0; clearn_TB=1; door_closed_TB=1; timer_done_TB=0;
            #3 startn_TB=0; stopn_TB=1; clearn_TB=1; door_closed_TB=1; timer_done_TB=0;
            #3 startn_TB=0; stopn_TB=1; clearn_TB=1; door_closed_TB=0; timer_done_TB=0;
            #3 startn_TB=0; stopn_TB=1; clearn_TB=1; door_closed_TB=1; timer_done_TB=0;
            #3 startn_TB=0; stopn_TB=1; clearn_TB=1; door_closed_TB=1; timer_done_TB=1;
            #3 startn_TB=0; stopn_TB=1; clearn_TB=1; door_closed_TB=1; timer_done_TB=0;
            #3 startn_TB=1; stopn_TB=1; clearn_TB=1; door_closed_TB=1; timer_done_TB=1;
            #3;
        end 
endmodule

nivel3/magnetron/comb_logic/comb_logic_tb.vcd
$date
	Thu Apr 20 18:46:15 2023
$end
$version
	Icarus Verilog
$end
$timescale
	1ps
$end
$scope module comb_logic_tb $end
$var reg 1 ! clearn_TB $end
$var reg 1 " door_closed_TB $end
$var reg 1 # startn_TB $end
$var reg 1 $ stopn_TB $end
$var reg 1 % timer_done_TB $end
$scope module DUT $end
$var wire 1 ! clearn $end
$var wire 1 " door_closed $end
$var wire 1 # startn $end
$var wire 1 $ stopn $end
$var wire 1 % timer_done $end
$var reg 1 & reset $end
$var reg 1 ' set $end
$upscope $end
$upscope $end
$enddefinitions $end
$comment Show the parameter values. $end
$dumpall
$end
#0
$dumpvars
0'
1&
1%
1$
1#
1"
1!
$end
#3000
0&
1'
0%
0#
#6000
1&
0'
1%
0!
#9000
0&
1'
0%
1!
#12000
1&
0'
0$
#15000
0&
1'
1$
#18000
1&
0'
0"
#21000
0&
1'
1"
#24000
1&
0'
1%
#27000
0&
1'
0%
#30000
1&
0'
1%
1#
