nivel1/nivel2/magnetron/latch_sr/latch_sr.v
module latch_sr(input wire set, reset,
                output reg mag_on); // mag_on seria a saida Q do latch SR padrao

  always @*
    
    if (set == 0 && reset == 0) begin
      mag_on <= mag_on;
    end
    else if (set == 0 && reset == 1) begin
      mag_on <= 0;
    end
    else if (set == 1 && reset == 0) begin
      mag_on <= 1;
    end
    else if (set == 1 && reset == 1) begin
      mag_on <= 0;
    end
    
endmodule

nivel1/nivel2/magnetron/comb_logic/comb_logic.v
module comb_logic(input wire startn, stopn, 
                  clearn, door_closed, timer_done,
                  output reg set, reset);

    always @(startn or stopn or clearn or
             door_closed or timer_done) 

        begin
            if ((!startn) && (stopn) && (clearn) && (door_closed) && (!timer_done))
                set = 1;
            else
                set = 0;
            
            if ((startn) || (!stopn) || (!clearn) || (!door_closed) || (timer_done))
                reset = 1;
            else
                reset = 0;
        end
endmodule

nivel1/nivel2/magnetron/magnetron.v
`include "comb_logic/comb_logic.v"
`include "latch_sr/latch_sr.v"

module magnetron(input wire startn, stopn, 
                 clearn, door_closed, timer_done,
                 output wire Q);

    wire set_wire, reset_wire;

    comb_logic comb_logic(startn, stopn, clearn, door_closed, timer_done, set_wire, reset_wire);


    latch_sr latch_sr(set_wire, reset_wire, Q);

endmodule

nivel1/nivel2/magnetron/magnetron_tb.v
`timescale 1ns/1ps
`include "magnetron.v"

module magnetron_tb();

    reg startn_TB, stopn_TB, clearn_TB, door_closed_TB, timer_done_TB;
    wire Q_TB;

    magnetron DUT(.startn(startn_TB),.stopn(stopn_TB),.clearn(clearn_TB),.door_closed(door_closed_TB),.timer_done(timer_done_TB), .Q(Q_TB));

    initial 
        begin
            
            $dumpfile("magnetron_tb.vcd");
            $dumpvars(0, magnetron_tb);

            startn_TB=1; stopn_TB=1; clearn_TB=1; door_closed_TB=1; timer_done_TB=1;
            #3 startn_TB=0; stopn_TB=1; clearn_TB=1; door_closed_TB=1; timer_done_TB=0;
            #3 startn_TB=0; stopn_TB=1; clearn_TB=0; door_closed_TB=1; timer_done_TB=1;
            #3 startn_TB=0; stopn_TB=1; clearn_TB=1; door_closed_TB=1; timer_done_TB=0;
            #3 startn_TB=0; stopn_TB=0; clearn_TB=1; door_closed_TB=1; timer_done_TB=0;
            #3 startn_TB=0; stopn_TB=1; clearn_TB=1; door_closed_TB=1; timer_done_TB=0;
            #3 startn_TB=0; stopn_TB=1; clearn_TB=1; door_closed_TB=0; timer_done_TB=0;
            #3 startn_TB=0; stopn_TB=1; clearn_TB=1; door_closed_TB=1; timer_done_TB=0;
            #3 startn_TB=0; stopn_TB=1; clearn_TB=1; door_closed_TB=1; timer_done_TB=1;
            #3 startn_TB=0; stopn_TB=1; clearn_TB=1; door_closed_TB=1; timer_done_TB=0;
            #3 startn_TB=0; stopn_TB=1; clearn_TB=1; door_closed_TB=1; timer_done_TB=0;
            #3 startn_TB=1; stopn_TB=1; clearn_TB=1; door_closed_TB=1; timer_done_TB=1;
            #3;
        end
        
endmodule

nivel1/nivel2/magnetron/magnetron_tb.vcd
$date
	Fri Apr 21 22:22:32 2023
$end
$version
	Icarus Verilog
$end
$timescale
	1ps
$end
$scope module magnetron_tb $end
$var wire 1 ! Q_TB $end
$var reg 1 " clearn_TB $end
$var reg 1 # door_closed_TB $end
$var reg 1 $ startn_TB $end
$var reg 1 % stopn_TB $end
$var reg 1 & timer_done_TB $end
$scope module DUT $end
$var wire 1 " clearn $end
$var wire 1 # door_closed $end
$var wire 1 $ startn $end
$var wire 1 % stopn $end
$var wire 1 & timer_done $end
$var wire 1 ' set_wire $end
$var wire 1 ( reset_wire $end
$var wire 1 ! Q $end
$scope module comb_logic $end
$var wire 1 " clearn $end
$var wire 1 # door_closed $end
$var wire 1 $ startn $end
$var wire 1 % stopn $end
$var wire 1 & timer_done $end
$var reg 1 ( reset $end
$var reg 1 ' set $end
$upscope $end
$scope module latch_sr $end
$var wire 1 ( reset $end
$var wire 1 ' set $end
$var reg 1 ! mag_on $end
$upscope $end
$upscope $end
$upscope $end
$enddefinitions $end
$comment Show the parameter values. $end
$dumpall
$end
#0
$dumpvars
1(
0'
1&
1%
1$
1#
1"
0!
$end
#3000
1!
0(
1'
0&
0$
#6000
0!
1(
0'
1&
0"
#9000
1!
0(
1'
0&
1"
#12000
0!
1(
0'
0%
#15000
1!
0(
1'
1%
#18000
0!
1(
0'
0#
#21000
1!
0(
1'
1#
#24000
0!
1(
0'
1&
#27000
1!
0(
1'
0&
#33000
0!
1(
0'
1&
1$
