nivel1/nivel2/decoder_7seg/decoder.v
module decoder (output wire [6:0] OutMinutos, OutDezenaSeg, OutUnidadeSeg,
                input wire [3:0] Minutos, DezenaSeg, UnidadeSeg);


        assign OutMinutos = (Minutos == 4'b0000) ? 7'b000_0001 : 
                            (Minutos == 4'b0001) ? 7'b100_1111 : 
                            (Minutos == 4'b0010) ? 7'b001_0010 : 
                            (Minutos == 4'b0011) ? 7'b000_0110 : 
                            (Minutos == 4'b0100) ? 7'b100_1100 : 
                            (Minutos == 4'b0101) ? 7'b010_0100 : 
                            (Minutos == 4'b0110) ? 7'b010_0000 : 
                            (Minutos == 4'b0111) ? 7'b000_1111 : 
                            (Minutos == 4'b1000) ? 7'b000_0000 : 
                            (Minutos == 4'b1001) ? 7'b000_1100 : 7'b111_1111;


        assign OutDezenaSeg =   (DezenaSeg == 4'b0000) ? 7'b000_0001 : 
                                (DezenaSeg == 4'b0001) ? 7'b100_1111 : 
                                (DezenaSeg == 4'b0010) ? 7'b001_0010 : 
                                (DezenaSeg == 4'b0011) ? 7'b000_0110 : 
                                (DezenaSeg == 4'b0100) ? 7'b100_1100 : 
                                (DezenaSeg == 4'b0101) ? 7'b010_0100 : 
                                (DezenaSeg == 4'b0110) ? 7'b010_0000 : 
                                (DezenaSeg == 4'b0111) ? 7'b000_1111 : 
                                (DezenaSeg == 4'b1000) ? 7'b000_0000 : 
                                (DezenaSeg == 4'b1001) ? 7'b000_1100 : 7'b111_1111;

        assign OutUnidadeSeg =  (UnidadeSeg == 4'b0000) ? 7'b000_0001 : 
                                (UnidadeSeg == 4'b0001) ? 7'b100_1111 : 
                                (UnidadeSeg == 4'b0010) ? 7'b001_0010 : 
                                (UnidadeSeg == 4'b0011) ? 7'b000_0110 : 
                                (UnidadeSeg == 4'b0100) ? 7'b100_1100 : 
                                (UnidadeSeg == 4'b0101) ? 7'b010_0100 : 
                                (UnidadeSeg == 4'b0110) ? 7'b010_0000 : 
                                (UnidadeSeg == 4'b0111) ? 7'b000_1111 : 
                                (UnidadeSeg == 4'b1000) ? 7'b000_0000 : 
                                (UnidadeSeg == 4'b1001) ? 7'b000_1100 : 7'b111_1111;
endmodule

nivel1/nivel2/decoder_7seg/decoder_tb.v
`include "decoder.v"
`timescale 1ns/1ns
module decoder_tb;

  reg [3:0] Minutos;
  reg [3:0] DezenaSeg;
  
  reg [3:0] UnidadeSeg;

  wire [6:0] OutMinutos;
  wire [6:0] OutDezenaSeg;
  wire [6:0] OutUnidadeSeg;


  decoder dut (
    .OutMinutos(OutMinutos),
    .OutDezenaSeg(OutDezenaSeg),
    .OutUnidadeSeg(OutUnidadeSeg),
    .Minutos(Minutos),
    .DezenaSeg(DezenaSeg),
    .UnidadeSeg(UnidadeSeg) );

    initial begin
        $dumpfile("decoder_tb.vcd");
        $dumpvars(0, decoder_tb);

        Minutos = 4'b0000; 
        DezenaSeg = 4'b0000; 
        UnidadeSeg = 4'b0000;

        #5 Minutos = 4'b0001; 
        DezenaSeg = 4'b0001; 
        UnidadeSeg = 4'b0001;

        #5 Minutos = 4'b0010; 
        DezenaSeg = 4'b0010; 
        UnidadeSeg = 4'b0010;

        #5 Minutos = 4'b0011; 
        DezenaSeg = 4'b0011; 
        UnidadeSeg = 4'b0011;

        #5 Minutos = 4'b0100; 
        DezenaSeg = 4'b0100; 
        UnidadeSeg = 4'b0100;

        #5 Minutos = 4'b0101; 
        DezenaSeg = 4'b0101; 
        UnidadeSeg = 4'b0101;

        #5 Minutos = 4'b0110; 
        DezenaSeg = 4'b0110; 
        UnidadeSeg = 4'b0110;

        #5 Minutos = 4'b0111; 
        DezenaSeg = 4'b0111; 
        UnidadeSeg = 4'b0111;

        #5 Minutos = 4'b1000; 
        DezenaSeg = 4'b1000; 
        UnidadeSeg = 4'b1000;

        #5 Minutos = 4'b1001; 
        DezenaSeg = 4'b1001; 
        UnidadeSeg = 4'b1001;
    end

endmodule

nivel1/nivel2/decoder_7seg/decoder_tb.vcd
$date
	Tue Apr 25 20:54:08 2023
$end
$version
	Icarus Verilog
$end
$timescale
	1ns
$end
$scope module decoder_tb $end
$var wire 7 ! OutUnidadeSeg [6:0] $end
$var wire 7 " OutMinutos [6:0] $end
$var wire 7 # OutDezenaSeg [6:0] $end
$var reg 4 $ DezenaSeg [3:0] $end
$var reg 4 % Minutos [3:0] $end
$var reg 4 & UnidadeSeg [3:0] $end
$scope module dut $end
$var wire 4 ' DezenaSeg [3:0] $end
$var wire 4 ( Minutos [3:0] $end
$var wire 4 ) UnidadeSeg [3:0] $end
$var wire 7 * OutUnidadeSeg [6:0] $end
$var wire 7 + OutMinutos [6:0] $end
$var wire 7 , OutDezenaSeg [6:0] $end
$upscope $end
$upscope $end
$enddefinitions $end
#0
$dumpvars
b1 ,
b1 +
b1 *
b0 )
b0 (
b0 '
b0 &
b0 %
b0 $
b1 #
b1 "
b1 !
$end
#5
b1001111 !
b1001111 *
b1001111 #
b1001111 ,
b1001111 "
b1001111 +
b1 &
b1 )
b1 $
b1 '
b1 %
b1 (
#10
b10010 !
b10010 *
b10010 #
b10010 ,
b10010 "
b10010 +
b10 &
b10 )
b10 $
b10 '
b10 %
b10 (
#15
b110 !
b110 *
b110 #
b110 ,
b110 "
b110 +
b11 &
b11 )
b11 $
b11 '
b11 %
b11 (
#20
b1001100 !
b1001100 *
b1001100 #
b1001100 ,
b1001100 "
b1001100 +
b100 &
b100 )
b100 $
b100 '
b100 %
b100 (
#25
b100100 !
b100100 *
b100100 #
b100100 ,
b100100 "
b100100 +
b101 &
b101 )
b101 $
b101 '
b101 %
b101 (
#30
b100000 !
b100000 *
b100000 #
b100000 ,
b100000 "
b100000 +
b110 &
b110 )
b110 $
b110 '
b110 %
b110 (
#35
b1111 !
b1111 *
b1111 #
b1111 ,
b1111 "
b1111 +
b111 &
b111 )
b111 $
b111 '
b111 %
b111 (
#40
b0 !
b0 *
b0 #
b0 ,
b0 "
b0 +
b1000 &
b1000 )
b1000 $
b1000 '
b1000 %
b1000 (
#45
b1100 !
b1100 *
b1100 #
b1100 ,
b1100 "
b1100 +
b1001 &
b1001 )
b1001 $
b1001 '
b1001 %
b1001 (
