nivel2_timer/nivel3_timer/contador_mod10.v
`timescale 1ns/1ps

module contador_mod10 (
    input wire clk,          // sinal de clock
    input wire loadn,        
  	input wire [3:0] data,   // valor inicial do contador
    input wire clearn,       // sinal de reset em nível baixo
    input wire en,           // sinal de habilitação em nível alto
    output wire tc,
    output wire zero,
  	output reg [3:0] ones // saída do contador
);

  assign zero = (ones == 4'b0000) ? 1'b1 : 1'b0;
  assign tc = en & zero;

  always @(posedge clk) begin
    if (~loadn) begin
        ones <= data; // reinicia o contador com o valor de 'data'
    end else if (~clearn) begin
        ones <= 3'b000; // zera o contador quando 'clearn' está em nível baixo
    end else if (en) begin
        if (ones == 4'b0000) begin
            ones <= 4'b1001; // volta a contar a partir de 9 quando atinge 0
        end else begin
            ones <= ones - 1; // subtrai 1 do contador
        end
    end
  end

endmodule

nivel3/timer/contador_mod10_tb.v
`include "contador_mod10.v"
`timescale 1ns/1ps

module contador_mod10_tb();

    reg clk;
    reg loadn;
    reg [3:0] data;
    reg clearn;
    reg en;
    wire tc;
    wire zero;
    wire [3:0] ones;
    integer i;

    contador_mod10 dut(
        clk,
        loadn,
        data,
        clearn,
        en,
        tc,
        zero,
        ones
    );

    initial begin
        clk = 1'b0;
    end

    initial begin
        $dumpfile("contador_mod10_tb.vcd");
        $dumpvars(0, dut);

        loadn = 1'b1;
        en = 1'b0;
        clearn = 1'b1;
        data = 4'b0110;

        #5 loadn = 1'b0;

        #5 loadn = 1'b1;

        #5 en = 1'b1;
    end

    initial begin
        #5 clk = ~clk;
        for (i = 0; i < 26; i = i + 1) begin
            #5 clk = ~clk;
        end
    end

endmodule

nivel2_timer/nivel3_timer/contador_mod10_tb.vcd
$date
	Fri Apr 21 13:06:55 2023
$end
$version
	Icarus Verilog
$end
$timescale
	1ps
$end
$scope module contador_mod10_tb $end
$scope module dut $end
$var wire 1 ! clearn $end
$var wire 1 " clk $end
$var wire 4 # data [3:0] $end
$var wire 1 $ en $end
$var wire 1 % loadn $end
$var wire 1 & tc $end
$var wire 1 ' zero $end
$var reg 4 ( ones [3:0] $end
$upscope $end
$upscope $end
$enddefinitions $end
$comment Show the parameter values. $end
$dumpall
$end
#0
$dumpvars
bx (
x'
0&
1%
0$
b110 #
0"
1!
$end
#5000
0'
b110 (
1"
0%
#10000
0"
1%
#15000
b101 (
1"
1$
#20000
0"
#25000
b100 (
1"
#30000
0"
#35000
b11 (
1"
#40000
0"
#45000
b10 (
1"
#50000
0"
#55000
b1 (
1"
#60000
0"
#65000
1&
1'
b0 (
1"
#70000
0"
#75000
0&
0'
b1001 (
1"
#80000
0"
#85000
b1000 (
1"
#90000
0"
#95000
b111 (
1"
#100000
0"
#105000
b110 (
1"
#110000
0"
#115000
b101 (
1"
#120000
0"
#125000
b100 (
1"
#130000
0"
#135000
b11 (
1"
