nivel1/nivel2/entrada_timer_controle/mux/mux.v
module mux(
    input wire enablen,
    input wire signal,
    input clk,
    output reg pgt_1Hz
);

    always @(*) begin
        if (enablen == 1'b0) begin
            pgt_1Hz = signal;
        end

        else
            pgt_1Hz = clk;
    end
    
endmodule

nivel1/nivel2/entrada_timer_controle/mux/mux_tb.v
`timescale 1ns/1ns
`include "mux.v"

module mux_tb;

    reg enablen_tb, signal_tb, clk_tb;
  	wire pgt_1Hz_tb;

  	mux dut(
        .enablen(enablen_tb), .signal(signal_tb), .clk(clk_tb), 
        .pgt_1Hz(pgt_1Hz_tb)
    );

    initial begin

        $dumpfile("mux_tb.vcd");
        $dumpvars(0, mux_tb);

        enablen_tb=1; signal_tb=0; clk_tb=1;
        #5 enablen_tb=0; signal_tb=0; clk_tb=1;
        #5 enablen_tb=1; signal_tb=1; clk_tb=0;
        #5 enablen_tb=0; signal_tb=1; clk_tb=0;
        #5 enablen_tb=1; signal_tb=1; clk_tb=1;
        #5 enablen_tb=0; signal_tb=1; clk_tb=1;
        #5 enablen_tb=1; signal_tb=0; clk_tb=0;
        #5 enablen_tb=0; signal_tb=0; clk_tb=0;
        
    end

endmodule

nivel1/nivel2/entrada_timer_controle/mux/mux_tb.vcd
$date
	Sat Apr 22 23:13:18 2023
$end
$version
	Icarus Verilog
$end
$timescale
	1ns
$end
$scope module mux_tb $end
$var wire 1 ! pgt_1Hz_tb $end
$var reg 1 " clk_tb $end
$var reg 1 # enablen_tb $end
$var reg 1 $ signal_tb $end
$scope module dut $end
$var wire 1 " clk $end
$var wire 1 # enablen $end
$var wire 1 $ signal $end
$var reg 1 ! pgt_1Hz $end
$upscope $end
$upscope $end
$enddefinitions $end
#0
$dumpvars
0$
1#
1"
1!
$end
#5
0!
0#
#10
0"
1$
1#
#15
1!
0#
#20
1"
1#
#25
0#
#30
0!
0"
0$
1#
#35
0#
