nivel1/nivel2/entrada_timer_controle/counter_freq/counter_freq.v
module counter_freq(
    input clk,
    output reg clk_out
);

    reg [5:0] count = 6'b000000;
    initial clk_out = 1'b0;

    always @(posedge clk) begin
        count = count + 1'b1;
        if (count >= 50) begin
            count = 6'b000000;
            clk_out = !clk_out;
        end
    end

endmodule

nivel1/nivel2/entrada_timer_controle/counter_freq/counter_freq_tb.v
`timescale 1ns/1ns
`include "counter_freq.v"

module counter_freq_tb;
    reg clk_tb;
    wire clk_out_tb;

    counter_freq dut(
        .clk(clk_tb),
        .clk_out(clk_out_tb)
    );
  
    initial begin

        $dumpfile("counter_freq_tb.vcd");
        $dumpvars(0, counter_freq_tb);
        #1 clk_tb = 1'b0;

        repeat(200)
            #1 clk_tb = ~clk_tb;
    end
endmodule

nivel1/nivel2/entrada_timer_controle/counter_freq/counter_freq_tb.vcd
$date
	Sat Apr 22 22:56:59 2023
$end
$version
	Icarus Verilog
$end
$timescale
	1ns
$end
$scope module counter_freq_tb $end
$var wire 1 ! clk_out_tb $end
$var reg 1 " clk_tb $end
$scope module dut $end
$var wire 1 " clk $end
$var reg 1 ! clk_out $end
$var reg 6 # count [5:0] $end
$upscope $end
$upscope $end
$enddefinitions $end
#0
$dumpvars
b0 #
x"
0!
$end
#1
0"
#2
b1 #
1"
#3
0"
#4
b10 #
1"
#5
0"
#6
b11 #
1"
#7
0"
#8
b100 #
1"
#9
0"
#10
b101 #
1"
#11
0"
#12
b110 #
1"
#13
0"
#14
b111 #
1"
#15
0"
#16
b1000 #
1"
#17
0"
#18
b1001 #
1"
#19
0"
#20
b1010 #
1"
#21
0"
#22
b1011 #
1"
#23
0"
#24
b1100 #
1"
#25
0"
#26
b1101 #
1"
#27
0"
#28
b1110 #
1"
#29
0"
#30
b1111 #
1"
#31
0"
#32
b10000 #
1"
#33
0"
#34
b10001 #
1"
#35
0"
#36
b10010 #
1"
#37
0"
#38
b10011 #
1"
#39
0"
#40
b10100 #
1"
#41
0"
#42
b10101 #
1"
#43
0"
#44
b10110 #
1"
#45
0"
#46
b10111 #
1"
#47
0"
#48
b11000 #
1"
#49
0"
#50
b11001 #
1"
#51
0"
#52
b11010 #
1"
#53
0"
#54
b11011 #
1"
#55
0"
#56
b11100 #
1"
#57
0"
#58
b11101 #
1"
#59
0"
#60
b11110 #
1"
#61
0"
#62
b11111 #
1"
#63
0"
#64
b100000 #
1"
#65
0"
#66
b100001 #
1"
#67
0"
#68
b100010 #
1"
#69
0"
#70
b100011 #
1"
#71
0"
#72
b100100 #
1"
#73
0"
#74
b100101 #
1"
#75
0"
#76
b100110 #
1"
#77
0"
#78
b100111 #
1"
#79
0"
#80
b101000 #
1"
#81
0"
#82
b101001 #
1"
#83
0"
#84
b101010 #
1"
#85
0"
#86
b101011 #
1"
#87
0"
#88
b101100 #
1"
#89
0"
#90
b101101 #
1"
#91
0"
#92
b101110 #
1"
#93
0"
#94
b101111 #
1"
#95
0"
#96
b110000 #
1"
#97
0"
#98
b110001 #
1"
#99
0"
#100
1!
b0 #
1"
#101
0"
#102
b1 #
1"
#103
0"
#104
b10 #
1"
#105
0"
#106
b11 #
1"
#107
0"
#108
b100 #
1"
#109
0"
#110
b101 #
1"
#111
0"
#112
b110 #
1"
#113
0"
#114
b111 #
1"
#115
0"
#116
b1000 #
1"
#117
0"
#118
b1001 #
1"
#119
0"
#120
b1010 #
1"
#121
0"
#122
b1011 #
1"
#123
0"
#124
b1100 #
1"
#125
0"
#126
b1101 #
1"
#127
0"
#128
b1110 #
1"
#129
0"
#130
b1111 #
1"
#131
0"
#132
b10000 #
1"
#133
0"
#134
b10001 #
1"
#135
0"
#136
b10010 #
1"
#137
0"
#138
b10011 #
1"
#139
0"
#140
b10100 #
1"
#141
0"
#142
b10101 #
1"
#143
0"
#144
b10110 #
1"
#145
0"
#146
b10111 #
1"
#147
0"
#148
b11000 #
1"
#149
0"
#150
b11001 #
1"
#151
0"
#152
b11010 #
1"
#153
0"
#154
b11011 #
1"
#155
0"
#156
b11100 #
1"
#157
0"
#158
b11101 #
1"
#159
0"
#160
b11110 #
1"
#161
0"
#162
b11111 #
1"
#163
0"
#164
b100000 #
1"
#165
0"
#166
b100001 #
1"
#167
0"
#168
b100010 #
1"
#169
0"
#170
b100011 #
1"
#171
0"
#172
b100100 #
1"
#173
0"
#174
b100101 #
1"
#175
0"
#176
b100110 #
1"
#177
0"
#178
b100111 #
1"
#179
0"
#180
b101000 #
1"
#181
0"
#182
b101001 #
1"
#183
0"
#184
b101010 #
1"
#185
0"
#186
b101011 #
1"
#187
0"
#188
b101100 #
1"
#189
0"
#190
b101101 #
1"
#191
0"
#192
b101110 #
1"
#193
0"
#194
b101111 #
1"
#195
0"
#196
b110000 #
1"
#197
0"
#198
b110001 #
1"
#199
0"
#200
0!
b0 #
1"
