nivel1/nivel2/timer_min_sec/nivel3_timer/contador_mod6.v

module contador_mod6 (
    input wire clk,          // sinal de clock
    input loadn,        
  	input wire [3:0] data,   // valor inicial do contador
    input clearn,       // sinal de reset em nível baixo
    input en,           // sinal de habilitação em nível alto
    output wire tc,
    output wire zero,
  	output reg [3:0] tens // saída do contador
);
  always @ (negedge clearn) // lembrar de trocar o reset e o stop (feito)
  begin
    tens = 4'b0000;
  end
  assign zero = (tens == 4'b0000) ? 1'b1 : 1'b0;
  assign tc = en & zero;

  always @(posedge clk) begin
    if (en)
        if (tens == 4'b0000) begin
            tens <= 4'b0101; // volta a contar a partir de 5 quando atinge 0
        end else 
            tens <= tens - 4'b0001; // subtrai 1 do contador
        
    else begin
      if (~loadn)
          tens <= data; // reinicia o contador com o valor de 'data'
    end
  end

endmodule

nivel1/nivel2/timer_min_sec/nivel3_timer/contador_mod6_tb.v
`include "contador_mod6.v"
`timescale 1ns/1ps

module contador_mod6_tb ();
    reg clk, loadn,clearn,en;
  	reg [3:0] data;
  	wire [3:0] tens;
    wire zero, tc;
    integer i;


  contador_mod6 dut(clk, loadn, data, en, clearn, tc, zero, tens);
  initial
    begin
      $dumpfile("contador_mod6_teste.vcd");
      $dumpvars(0,contador_mod6_tb);
  
  assign loadn = 1;
  assign en = 0;
  assign clearn = 1;
  assign data = 3'b000;

  #6 assign data = 3'b101;

  #5 assign loadn = 0;

  #5 assign clearn = 1;

  #5 assign loadn = 1;

  #4 assign en = 1;
    end

initial
  begin
    clk = 1'b0;
  end

initial
  begin
    #5 clk = ~clk;
    for(i = 0; i < 26; i= i + 1)
        begin
          #5 clk = ~clk;
        end
  end
endmodule

nivel1/nivel2/timer_min_sec/nivel3_timer/contador_mod6_teste.vcd
$date
	Tue Apr 25 20:36:57 2023
$end
$version
	Icarus Verilog
$end
$timescale
	1ps
$end
$scope module contador_mod6_tb $end
$var wire 1 ! zero $end
$var wire 4 " tens [3:0] $end
$var wire 1 # tc $end
$var reg 1 $ clearn $end
$var reg 1 % clk $end
$var reg 4 & data [3:0] $end
$var reg 1 ' en $end
$var reg 1 ( loadn $end
$var integer 32 ) i [31:0] $end
$scope module dut $end
$var wire 1 ' clearn $end
$var wire 1 % clk $end
$var wire 4 * data [3:0] $end
$var wire 1 $ en $end
$var wire 1 ( loadn $end
$var wire 1 # tc $end
$var wire 1 ! zero $end
$var reg 4 + tens [3:0] $end
$upscope $end
$upscope $end
$enddefinitions $end
#0
$dumpvars
b0 +
b0 *
bx )
1(
0'
b0 &
0%
1$
1#
b0 "
1!
$end
#5000
0#
0!
b101 "
b101 +
b0 )
1%
#6000
b101 &
b101 *
#10000
b1 )
0%
#11000
0(
#15000
b100 "
b100 +
b10 )
1%
#20000
b11 )
0%
#21000
1(
#25000
b11 "
b11 +
1'
b100 )
1%
#30000
b101 )
0%
#35000
b10 "
b10 +
b110 )
1%
#40000
b111 )
0%
#45000
b1 "
b1 +
b1000 )
1%
#50000
b1001 )
0%
#55000
1#
1!
b0 "
b0 +
b1010 )
1%
#60000
b1011 )
0%
#65000
0#
0!
b101 "
b101 +
b1100 )
1%
#70000
b1101 )
0%
#75000
b100 "
b100 +
b1110 )
1%
#80000
b1111 )
0%
#85000
b11 "
b11 +
b10000 )
1%
#90000
b10001 )
0%
#95000
b10 "
b10 +
b10010 )
1%
#100000
b10011 )
0%
#105000
b1 "
b1 +
b10100 )
1%
#110000
b10101 )
0%
#115000
1#
1!
b0 "
b0 +
b10110 )
1%
#120000
b10111 )
0%
#125000
0#
0!
b101 "
b101 +
b11000 )
1%
#130000
b11001 )
0%
#135000
b100 "
b100 +
b11010 )
1%
